<author lang="ar">
	<documents>
		<document><![CDATA[Ø§ÙˆÙˆÙˆÙˆÙˆÙˆÙˆÙˆÙˆÙ‡ Ø³Ø¯Ø§Ø¯Ù‡Ø§Ø§Ø§Ø§Ø§Ø§Ø§Ø§Ø§Ø§Ø§Ø§ ÙÙŠ Ø§Ù„Ù…Ø±Ù…ÙŠ .. Ø´Ù†Ùˆ Ù‡Ø°Ø§Ø§Ø§Ø§Ø§Ø§Ø§Ø§Ø§Ø§Ø§Ø§Ø§Ø§Ø§Ø§ ðŸ˜‚ðŸ˜‚ðŸ˜‚ðŸ˜‚ https://t.co/KD8rtPqG8b]]></document>
		<document><![CDATA[Ø§Ù„Ø­Ù…Ø¯ Ù„Ù„Ù‡ Ø­Ù…Ø§ÙŠØ§ Ù…Ø¨ÙŠØ¹Ø±ÙØ´ ÙŠÙ„Ø¹Ø¨ Ø¨Ù„Ø§ÙŠ Ø³ØªÙŠØ´Ù† ðŸ˜‚ðŸ˜‚ðŸ˜‚ https://t.co/cLGDVXoNMO]]></document>
		<document><![CDATA[Ø§Ø¨Ø¯Ø¡ ÙŠÙˆÙ…Ùƒ ðŸ˜Š https://t.co/LqPOfjEglV]]></document>
		<document><![CDATA[Ù…Ø´ Ø¹Ø§Ø±Ù Ù„ÙŠÙ‡ Ø¹Ù†Ø¯ÙŠ Ø§Ø­Ø³Ø§Ø³ Ø§Ù† Ø§Ù„Ø³ÙŠØ³ÙŠ Ù‡ÙŠÙƒØ³Ø¨ ðŸ˜ƒ]]></document>
		<document><![CDATA[Ø§Ø¨ÙˆÙŠØ§ â¤ https://t.co/Z56FXEUFxC]]></document>
		<document><![CDATA[Ø§Ù†Ø§ ÙƒØ¯Ù‡ ÙŠØ§Ù…Ø³ØªØ± Ù…Ø­Ù…Ø¯ ÙˆØ±Ù‚ÙŠ ÙƒÙ„Ù‡ ØªÙ…Ø§Ù… 
Ø§Ù‡Ø§ .. Ø§Ù†Ø§ Ù‡ØªØµÙ„ Ø¨ÙŠÙƒÙŠ Ø§Ø¨Ù„Øº ØªÙŠØ¬ÙŠ ØªØ³Ù„Ù… Ø§Ù„Ø´ØºÙ„ Ø§Ù…ØªÙŠ 

Ohhhhh luv u said â¤ .. thats amazing ðŸ˜‚ðŸ˜‚ðŸ˜‚ https://t.co/xEzpORaOcw]]></document>
		<document><![CDATA[Ø§Ø¨Ø¯Ø¡ ÙŠÙˆÙ…Ùƒ ðŸ˜ðŸ˜Š https://t.co/4AUcSUojEN]]></document>
		<document><![CDATA[Ø¨Ø­Ù‚ Ù‡Ø°Ø§ Ø§Ù„ØºÙŠØ« Ø§ÙØ±Ø¬Ù‡Ø§ Ù…Ù† Ø¹Ù†Ø¯Ùƒ ÙŠØ§Ø§Ø§Ø§Ø§Ø§Ø§Ø§Ø§ Ø±Ø¨ ðŸ˜ðŸ˜ðŸ˜]]></document>
		<document><![CDATA[ÙŠÙˆÙ…ÙŠØ§ Ø¨Ø±ÙƒØ¨ Ø§Ù„Ù…ØªØ±Ùˆ ÙˆØ§Ù†Ø§ Ù…Ø±ÙˆØ­ .. Ø§ØªÙ†ÙŠÙ† Ø¹ÙˆØ§Ø¬ÙŠØ² Ø§ØªØ®Ù†Ù‚ÙˆØ§ Ù…Ø¹ Ø¨Ø¹Ø¶ Ø¹Ø´Ø§Ù† ÙˆØ§Ø­Ø¯ Ù…Ù†Ù‡Ù… Ø²Ù‚ Ø§Ù„ØªØ§Ù†ÙŠ ÙˆÙ‡Ùˆ Ø¨ÙŠØ±ÙƒØ¨ .. ÙˆÙ‡Ø§ØªÙƒ Ø´ØªØ§ÙŠÙ… Ù…Ù† Ø§Ù„Ù„Ù‰ Ù‚Ù„Ø¨Ùƒ Ø¨ÙŠØ­Ø¨Ù‡Ø§ ÙˆÙ„Ø§ Ø§Ø¬Ø¯Ø¹Ù‡Ø§ Ù…Ø±Ù‡ Ø¨ØªØªØ®Ø§Ù†Ù‚ Ø¹Ù„Ù‰ Ø§Ù„Ù†Ø§ØµÙŠØ© .. Ø§Ù„Ù…Ø´ÙƒÙ„Ø© Ù…Ø´ Ù ÙƒØ¯Ù‡ .. Ø§Ù„Ù…Ø´ÙƒÙ„Ø© Ø§Ù† Ø§Ù„Ø§ØªÙ†ÙŠÙ† ÙˆÙ„Ø§Ø¯... https://t.co/H1tlMgRT1L]]></document>
		<document><![CDATA[Ø§ÙŠØªÙ‡Ø§ Ø§Ù„Ù†Ø§Ø®Ø¨Ø© ÙˆØ³Ø·Ùƒ Ø§Ù…Ø§Ù†Ø© ÙÙ„Ø§ ØªÙ‡Ø²ÙŠÙ‡ Ø§Ù„Ø§ Ù„Ù…Ù† ÙŠØ³ØªØ­Ù‚]]></document>
		<document><![CDATA[Ù…Ø¯Ø§Ø§Ø§Ø§Ø§Ø¯ Ø³ÙŠØ¯ÙŠ Ø§Ù„Ø¹Ø±ÙŠØ§Ù† Ù…Ø¯Ø§Ø§Ø§Ø§Ø§Ø§Ø§Ø¯ ðŸ˜‚ðŸ˜‚ðŸ˜‚ðŸ˜‚ðŸ˜‚ https://t.co/25sJEf95S7]]></document>
		<document><![CDATA[Ù‡ÙŠ Ø§Ù„Ù…Ø±Ù‡ ÙˆÙ„Ø§ Ø§Ù„Ø¨Øª Ø§Ù„Ù„Ù‰ Ø¨ØªØ±Ù‚Øµ Ù‚Ø¯Ø§Ù… Ø§Ù„Ù„Ø¬Ù†Ø© .. Ù‡Ù„ ÙÙŠ Ø±Ø§Ø¬Ù„ Ù…Ø³Ø¦ÙˆÙ„ Ø¹Ù†Ù‡Ø§ ÙˆÙ„Ø§ Ù‡Ùˆ Ø®ÙˆÙ„ ØŸ!!!]]></document>
		<document><![CDATA[Ù‡Ùˆ ØµØ­ÙŠØ­ Ù…ÙˆØ¶ÙˆØ¹ Ø¥ØªÙØ§Ù‚ÙŠØ© cismoa Ø¯Ù‡ Ø­ØµÙ„ Ø¨Ø¬Ø¯ ØŸ!!!!!!!!!]]></document>
		<document><![CDATA[Ø§Ø¨Ø¯Ø¡ ÙŠÙˆÙ…Ùƒ ðŸ˜Š https://t.co/qruRz9dHbj]]></document>
		<document><![CDATA[Ø¯Ù‡ Ø§Ø­Ù†Ø§ ØµÙŠØ§Ø¯ÙŠÙ† ÙŠØ§Ù„Ø§ ðŸ˜‚ðŸ˜‚ðŸ˜‚ https://t.co/cvoeteAEiP]]></document>
		<document><![CDATA[Ø§Ù„Ù„Ù‡Ù… ØµÙ„ Ø¹Ù„Ù‰ Ù…Ø­Ù…Ø¯ ÙˆØ§Ù„ Ù…Ø­Ù…Ø¯ ÙƒÙ…Ø§ ØµÙ„ÙŠØª Ø¹Ù„Ù‰ Ø§Ø¨Ø±Ø§Ù‡ÙŠÙ… ÙˆØ§Ù„ Ø§Ø¨Ø±Ø§Ù‡ÙŠÙ… Ø§Ù†Ùƒ Ø­Ù…ÙŠØ¯ Ù…Ø¬ÙŠØ¯ .. ÙˆØ¨Ø§Ø±Ùƒ Ø¹Ù„Ù‰ Ù…Ø­Ù…Ø¯ ÙˆØ§Ù„ Ù…Ø­Ù…Ø¯ ÙƒÙ…Ø§ Ø¨Ø§Ø±ÙƒØª Ø¹Ù„Ù‰ Ø§Ø¨Ø±Ø§Ù‡ÙŠÙ… ÙˆØ§Ù„ Ø§Ø¨Ø±Ø§Ù‡ÙŠÙ… Ø§Ù†Ùƒ Ø­Ù…ÙŠØ¯ Ù…Ø¬ÙŠØ¯ ðŸ˜â¤ https://t.co/p4NrWzxQlL]]></document>
		<document><![CDATA[Ù‡ÙˆÙ„ÙŠØ¯Ø§Ø§Ø§Ø§Ø§Ø§Ø§Ø§Ø§ÙŠ ðŸ˜‚ðŸ˜‚ðŸ˜‚ðŸ˜‚ðŸ˜‚ðŸ˜‚ðŸ˜‚ðŸ˜‚ https://t.co/r4k2hgxvSk]]></document>
		<document><![CDATA[ÙŠØ®Ø±Ø¨ÙŠØª Ø§Ù„Ø§Ø¨Ø¯Ø§Ø¹ ÙˆØ§Ù„Ø¶Ø­Ùƒ ðŸ˜‚ðŸ˜‚ðŸ˜ https://t.co/AAmdXnJzsd]]></document>
		<document><![CDATA[Mohamed Shwky
Ø§Ø­ÙØ¸ Ø§Ù„Ø±Ù‚ØµÙ‡ Ø¯ÙŠ ÙƒÙˆÙŠØ³ Ø¹Ø´Ø§Ù† Ù‡Ù†Ø±Ù‚ØµÙ‡Ø§ https://t.co/DVI3mjpTmB]]></document>
		<document><![CDATA[Ø®Ù„Ø§Øµ Ø®Ù„ØµØªÙˆØ§ !! ÙƒÙ„ Ø³Ù†Ø© ÙˆØ§Ù†ØªÙŠ Ø·ÙŠØ¨Ù‡ ÙŠØ§Ù…ÙŠ ÙˆÙŠØ§Ø³Øª Ø§Ù„Ù†Ø§Ø³ ÙˆÙŠØ§Ø³Øª Ø§Ù„ÙƒÙ„ .. Ø¹Ù„Ù‰ ÙÙƒØ±Ø© Ø¨Ù‚ÙŠ Ø³Øª Ø§Ù„ÙƒÙ„ Ù…ÙƒÙ†ØªØ´ Ù‡ØªØ¨Ù‚ÙŠ Ø§Ù… Ù…Ù† ØºÙŠØ±Ùƒ ðŸ˜‚ðŸ˜‚ðŸ˜‚]]></document>
		<document><![CDATA[Ø§Ø¨Ø¯Ø¡ ÙŠÙˆÙ…Ùƒ ðŸ˜Š https://t.co/g5uiSgLtzp]]></document>
		<document><![CDATA[Ø§Ø¨Ø¯Ø¡ ÙŠÙˆÙ…Ùƒ ðŸ˜Š https://t.co/lynnga2VB3]]></document>
		<document><![CDATA[ÙŠØ§Ø¯ÙŠÙ†ÙŠ Ø¹Ù„Ù‰ Ø§Ù„Ø¶Ø­Ùƒ .. Ø§ØªÙØ´Ø® Ù‚ÙØ§ Ø§Ø¨Ù† ÙˆØ²Ù‡ ðŸ˜‚ðŸ˜‚ðŸ˜‚ðŸ˜‚ðŸ˜‚ https://t.co/5qsRmbwwye]]></document>
		<document><![CDATA[Ø§Ù†Ø§ Ù…ØªØµÙˆØ±ØªØ´ Ù…Ø¹ Ø§Ù…ÙŠ ÙˆÙ„Ø§ Ù‚ÙˆÙ„ØªÙ„Ù‡Ø§ ÙƒÙ„ Ø³Ù†Ø© ÙˆØ§Ù†ØªÙŠ Ø·ÙŠØ¨Ø© .. Ø¹Ø´Ø§Ù† Ù‡ÙŠ Ù„Ø§ Ø¨ØªØ­Ø¨ Ø§Ù„ØªØµÙˆÙŠØ± ÙˆÙ„Ø§ Ø¨ØªØ­Ø¨Ù†ÙŠ Ø§Ø³Ø§Ø³Ø§ ðŸ˜ƒ]]></document>
		<document><![CDATA[Ø§Ù„Ù„Ù‡Ù… Ø²Ø¯ ÙÙŠ Ø¹ÙÙ…Ø± Ø£Ù…ÙŠ ÙˆØµØ­ØªÙ‡Ø§ .. ÙˆØ¥Ø¬Ø¹Ù„Ù†ÙŠ Ø³Ø¨Ø¨Ù‹Ø§ Ù…Ù† Ø£Ø³Ø¨Ø§Ø¨ ÙØ±Ø­ØªÙ‡Ø§ .. ÙˆÙ„Ø§ ØªÙƒÙˆÙŠ Ù‚Ù„Ø¨Ù‡Ø§ Ø¨Ù†Ø§Ø± ÙÙ‚Ø¯Ø§Ù†ÙŠ .. ÙˆÙ„Ø§ ØªØ­Ø±Ù…Ù‡Ø§ Ù…Ù† Ø§Ù„Ø³Ø¬ÙˆØ¯ Ø£Ù…Ø§Ù… Ø§Ù„ÙƒØ¹Ø¨Ø© ÙˆØ²ÙŠØ§Ø±ØªÙ‡Ø§  ðŸ¤²ðŸ»â¤ï¸]]></document>
		<document><![CDATA[ÙˆÙ„Ø§ ØµØ­Ø¨Ù‡ Ø§Ø­Ù„Ù‰ Ù…Ù† ØªØ¬Ù„Ù‰ Ø§Ù„Ø°Ø§Øª â¤]]></document>
		<document><![CDATA[ÙˆÙƒØ¹Ø§Ø¯Ù‡ Ø­Ù…Ø²Ø© Ù†Ù…Ø±Ù‡ ÙÙŠ ÙƒÙ„ Ø§Ù„Ø¨ÙˆÙ… Ù„Ø§Ø²Ù… ÙŠØ¹Ù„Ù… Ø¹Ù„Ù‰ Ù‚ÙØ§ Ø§Ù„Ø²Ø¨ÙˆÙ† ðŸ˜ƒðŸ˜ƒ

#Ø´ÙŠÙƒØ§ÙŠÙˆ_ÙŠØ§_Ø´ÙŠÙƒØ§ÙŠÙˆ_Ø³ÙˆØ§Ù‚Ù†Ø§_Ù…ÙÙŠØ´_Ø²ÙŠÙ‡]]></document>
		<document><![CDATA[Ø§Ø¨Ø¯Ø¡ ÙŠÙˆÙ…Ùƒ ðŸ˜ŠðŸ˜ŠðŸ˜Š https://t.co/X7qJq92kXL]]></document>
		<document><![CDATA[Ø§ÙˆÙˆÙˆÙˆÙˆÙˆÙˆÙˆÙˆÙˆÙˆÙˆÙ‡ .. Ø§Ù„Ø¬Ø¨Ù‡Ù‡ Ø·Ø§Ø§Ø§Ø§Ø§Ø§Ø§Ø±Øª ÙŠØ§ÙˆÙ„Ø¯Ù‰ Ø·Ø§Ø§Ø§Ø§Ø§Ø§Ø±Øª 
Ø§Ù†Ø§ Ù„Ù…Ø§ Ø§Ø­Ø¨ Ø§ØªØ³Ù„Ù‰ Ø§ØªÙØ±Ø¬ Ø¹ Ø§Ù„Ø²Ù…Ø§Ù„Ùƒ ÙˆÙ‡Ùˆ Ø¨ÙŠØªØºÙ„Ø¨ ðŸ˜‚ðŸ˜‚ðŸ˜‚ðŸ˜‚ https://t.co/EHJb8wEY3E]]></document>
		<document><![CDATA[Ù„Ø§ Ù„Ø§Ø¡ Ù„Ø§Ø¡ Ù„Ø§Ø§Ø§Ø§Ø§Ø§Ø§Ø§ .. Ø§Ø±Ø­Ù…ÙˆÙ†Ø§ ÙŠØ§Ø¬Ø¯Ø¹Ø§Ø§Ø§Ø§Ø§Ù† Ø§Ù†Ø§ Ø¯Ø§Ø®Ù„ Ø¹Ù„Ù‰ Ø¬ÙˆØ§Ø² Ù…Ø´ Ø¹Ø§ÙˆØ²Ù‡Ù… ÙŠØªÙÙ‚Ø¹ÙˆØ§ Ø§Ø¨ÙˆØ³ Ø§ÙŠØ¯Ùƒ .. ÙŠØ®Ø±Ø¨ÙŠØª Ø¯Ù…Ø§ØºÙƒ https://t.co/ciMauA95f0]]></document>
		<document><![CDATA[Ø³Ù†Ø¸Ù„ Ø§ÙˆÙÙŠØ§Ø¡ ðŸ˜‚ðŸ˜‚ðŸ˜‚]]></document>
		<document><![CDATA[Ø§Ø­Ù„Ù‰ Ø´Ø®Ø±Ù‡ Ù‡Ù†Ø§ Ø¹Ù†Ø¯ Ø§Ø¨Ùˆ Ø¹ÙØ§Ù ðŸ˜‚ðŸ˜‚ðŸ˜‚ https://t.co/IKAdcfBslg]]></document>
		<document><![CDATA[Ø§Ø©Ø©Ø©Ø©Ø©Ø©Ø©Ø©Ø©Ø©Ø©Ø©Ø©Ø©Ø©Ø©Ø©Ø© .. Ø¨ØµÙˆØª Ù‡Ø§Ù†ÙŠ Ø±Ù…Ø²Ù‰ Ù„Ù…Ø§ Ø§ØªØ®Ø¨Ø· ÙÙŠ Ø§Ù„Ù„Ø§Ù…Ø¤Ø®Ø°Ù‡ ÙÙŠ ÙÙŠÙ„Ù… #ØºØ¨ÙŠ_Ù…Ù†Ù‡_ÙÙŠÙ‡ https://t.co/tJtZZTKFLX]]></document>
		<document><![CDATA[ÙŠØ§ Ø¬Ù…Ø§Ø¹Ø© Ø­Ø¯ ÙŠÙ‚ÙˆÙ„ Ù„Ù„ÙÙ†Ø§Ù† Ø­Ø³ÙŠÙ† Ø§Ù„Ø¬Ø§Ø³Ù…Ù‰ Ø§Ù† Ø´ÙŠÙƒÙˆÙ„Ø§ØªØ© ÙƒØ§Ø¯Ø¨ÙˆØ±Ù‰ -Ø§Ù„Ù„Ù‰ Ø§Ù„Ø£Ø³ØªØ§Ø° Ù‡Ø§Ù†Ù‰ Ø±Ù…Ø²Ù‰ Ø¨ÙŠØ¯ÙŠÙ‡Ø§ Ù„Ù„ÙˆØ§Ø¯ Ø§Ù„ØµØºÙŠØ± ÙˆÙ‡Ùˆ Ù‚Ø§Ø¹Ø¯ ÙÙ‰... https://t.co/WddxDwAjLZ]]></document>
		<document><![CDATA[Ø®ÙŠØ± Ù…ØªØ§Ø¹ Ø§Ù„Ø¯Ù†ÙŠØ§ .. Ø²ÙˆØ¬Ø© ØµØ§Ù„Ø­Ø© â¤ https://t.co/hZQBOvQ2s0]]></document>
		<document><![CDATA[ØµØ¨Ø§Ø­ Ø§Ù„Ø®ÙŠØ± Ù„ÙŠ Ùˆ Ù„Ùƒ Ùˆ Ù„ÙƒÙ„ Ø´Ø®Øµ ÙŠØ¶Ø¹ ÙÙŠ Ù‚Ø±Ø§Ø±Ø© Ù†ÙØ³Ù‡ Ø§Ù†Ù‡ ÙŠØ³ØªØ­Ù‚ ÙŠÙˆÙ… Ø¬Ù…ÙŠÙ„ ÙˆÙ„Ø§ ÙŠØ£Ø¨Ù‡ Ù„Ù…Ø¹ÙƒØ±Ø§Øª Ø§Ù„Ù…Ø²Ø§Ø¬]]></document>
		<document><![CDATA[ÙƒÙ„Ù†Ø§ Ù…Ù† Ø¬ÙˆØ§Ù†Ø§ Ø§ØªØºÙŠØ±Ù†Ø§ ÙˆÙ…Ø¨Ù‚Ø§Ø´ Ø¹Ù†Ø¯Ù†Ø§ Ø·Ø§Ù‚Ø© Ù„Ø­Ø¯ ÙˆÙ…Ø¹Ø¯Ø´ Ø¹Ù†Ø¯Ù†Ø§ Ø·Ø§Ù‚Ø© Ù†Ø³Ø§Ù…Ø­ .. ÙˆØµÙ„Ù†Ø§ Ù„Ù…Ø±Ø­Ù„Ø© Ø§Ù† Ø§Ù„Ù„Ù‰ Ù…Ø´ Ù‡ÙŠØ³ØªØ¬Ø¯Ø¹ Ù…Ø¹Ø§Ù†Ø§ Ù…Ù„ÙˆØ´ ÙØ±ØµØ© ØªØ§Ù†ÙŠØ©]]></document>
		<document><![CDATA[Ø­Ø¯ ÙŠÙ‚ØªÙ„ Ø§Ù„Ø¨Øª Ø¯Ù‰ ðŸ˜‚ðŸ˜‚ðŸ˜‚ https://t.co/MJhULt9PHI]]></document>
		<document><![CDATA[ÙŠØ§ Ø£Ù‡ ÙŠØ§Ø§Ø§Ø§ Ø£Ù‡ ðŸ˜‚ðŸ˜‚ðŸ˜‚ðŸ˜‚ https://t.co/00RyVhriNV]]></document>
		<document><![CDATA[Ø§Ø¨Ø¯Ø¡ ÙŠÙˆÙ…Ùƒ ðŸ˜Š https://t.co/u2MZmHHV6G]]></document>
		<document><![CDATA[Ø§ÙˆÙˆÙˆÙˆÙˆÙˆÙˆÙˆÙˆÙ‡ .. Ø¯Ù…Ø±Ù‡Ø§Ø§Ø§Ø§Ø§Ø§ ÙƒÙˆØ§Ù‡Ø§Ø§Ø§Ø§Ø§Ø§Ø§Ø§ Ø§Ø­Ø±Ø¬ Ù…Ø±Ù…Ø§Ù‡Ø§Ø§Ø§Ø§Ø§Ø§Ø§Ø§ ðŸ˜‚ðŸ˜‚ðŸ˜‚ðŸ˜‚ https://t.co/A01VAwhnXw]]></document>
		<document><![CDATA[Ø§Ø¨Ø¯Ø¡ ÙŠÙˆÙ…Ùƒ â¤â¤â¤ https://t.co/YByB7IO6Lk]]></document>
		<document><![CDATA[Ù‡Ùˆ Ø§Ù†ØªÙŠ Ø¹Ø±ÙØªÙŠ Ù…Ù†ÙŠÙ† Ø§Ù† ÙƒÙ„Ù†Ø§ Ù…ØµØ·ÙÙŠ Ø§Ø¨Ùˆ Ø­Ø¬Ø± ÙˆØ§Ù†ØªÙŠ Ø¨ØªÙ‚ÙˆÙ„ÙŠÙ„ÙŠ Ø§Ù†ÙŠ Ø§ÙˆÙ„ ÙˆØ§Ø­Ø¯ Ù Ø­ÙŠØ§ØªÙƒ ðŸ˜®ðŸ˜‚ðŸ˜‚ðŸ˜‚]]></document>
		<document><![CDATA[Ù…Ù„Ø¹ÙˆÙ† Ø§Ù„ÙÙ‚Ø± .. Ø§Ù„Ø­Ù…Ø¯ Ù„Ù„Ù‡ â¤â¤ https://t.co/AwbUoGvPPh]]></document>
		<document><![CDATA[Ø±Ø¨Ù†Ø§ ÙŠØ§Ø®Ø¯ÙƒÙˆØ§ ðŸ˜‚ðŸ˜‚ðŸ˜‚ https://t.co/KgedtkV4sg]]></document>
		<document><![CDATA[Ø§Ø¨Ø¯Ø¡ ÙŠÙˆÙ…Ùƒ ðŸ˜Š https://t.co/7zlg7BQAKv]]></document>
		<document><![CDATA[Ø§Ø­Ù„Ù‰ Ø§Ù‡Ù„Ù‰ Ø¯Ù‡ ÙˆÙ„Ø§ Ø§ÙŠÙ‡ ðŸ˜ðŸ˜]]></document>
		<document><![CDATA["Ø¥Ù† ÙƒÙ†Øª Ù Ø§Ù„Ø·Ø±ÙŠÙ‚ Ø¥Ù„Ù‰ Ø§Ù„Ù„Ù‡ ÙØ£Ø±ÙƒØ¶ ØŒ ÙˆØ¥Ù† ØµÙŒØ¹Ø¨ Ø¹Ù„ÙŠÙƒ ÙÙ‡Ø±ÙˆÙ„ØŒ ÙˆØ¥Ù† ØªØ¹Ø¨Øª ÙØ¥Ù…Ø´ØŒ ÙˆØ¥Ù† Ù„Ù… ØªØ³ØªØ·Ø¹ ÙƒÙ„ Ù‡Ø°Ø§ ÙØ³Ø± ÙˆÙ„Ùˆ Ø­Ø¨ÙˆØ§ ØŒ ÙˆÙ„ÙƒÙ†... https://t.co/AJRBmj0VPj]]></document>
		<document><![CDATA[Ø§Ù„Ù„Ù‰ Ø§Ø®Ø¯ Ø§Ù„Ø´ÙˆØª Ø¯Ù‡ Ø¨Ø±Ù†Ø³ ÙˆØ§Ù„Ù„Ù‡ ðŸ˜Ž https://t.co/qJc6yT6mWQ]]></document>
		<document><![CDATA[ÙÙŠ Ø¥Ø­Ø¯Ù‰ Ø­ÙˆØ§Ø±Ø§ØªÙŠ Ù…Ø¹ Ø§Ù„Ù„Ù‡ Ù„Ù… Ø£ÙƒÙ† Ø£Ø³Ù…Ø¹ Ø¬ÙˆØ§Ø¨Ø§Ù‹ Ù…Ø·Ù„Ù‚Ø§Ù‹ Ø£Ùˆ Ù…Ù‚Ø§Ø·Ø¹Ù‡ .. ÙƒØ§Ù†Øª Ø§Ù„Ø³Ø§Ø¹Ø§Øª ÙƒÙ„Ù‡Ø§ Ù„ÙŠ ØŒ ÙƒÙ…Ø§ Ø£Ù†Ù†ÙŠ Ø¨ÙƒÙŠØªÙ Ø¯ÙˆÙ† Ø­Ø±Ø¬ ØŒ Ùˆ... https://t.co/Amj9ru4cdq]]></document>
		<document><![CDATA[ÙŠØ®Ø±Ø¨ÙŠØª Ø§Ù„Ø¶Ø­Ùƒ ðŸ˜‚ðŸ˜‚ðŸ˜‚ðŸ˜‚ https://t.co/nTLSlB68FD]]></document>
		<document><![CDATA[ÙÙƒØ±Ù†Ù‰ Ø¨ÙŠÙƒ Ø§Ù†Ù‡Ø§Ø±Ø¯Ø© ÙˆØ§Ù†Øª Ø¨ØªØ·Ù„Ø¨ Ù…Ù†Ù‰ Ø§Ù„Ø§Ø°Ù† ÙˆØ§Ù†Ø§ Ù…Ù†ÙØ¶Ù„Ùƒ ðŸ˜‚ðŸ˜‚ðŸ˜‚

 Ø£Ø­Ù…Ø¯ Ø®Ø§Ù„Ø¯ Ø­Ø³Ù† https://t.co/WWzEcviFBy]]></document>
		<document><![CDATA[Ø§ÙŠÙ‡ Ø§Ù„Ø¹Ø¸Ù…Ù‡ Ø¯Ù‰ â¤ https://t.co/qMIscNrepj]]></document>
		<document><![CDATA[ÙƒÙ„Ù‘Ù…Ø§ Ø£Ø³ØªØºÙÙŽØ±Øª Ø§Ù„Ù„ÙŽÙ‘Ù‡ Ø¥Ù†Ø­Ù„ØªÙ‘ Ø¹Ù†Ùƒ Ø¹ÙÙ‚Ø¯Ø© Ù…Ù† Ø¹ÙÙ‚Ø¯ Ù‡Ù…Ù‘Ùƒ Ùˆ Ø£Ù†Ù‡Ù„ØªÙ‘ Ø¹Ù„Ù‰ Ù‚Ù„Ø¨Ùƒ Ø§Ù„Ù†Ø¹Ù… ØŒØŒ Ø£Ø³ØªØºÙØ± Ø§Ù„Ù„Ù‡ Ø§Ù„Ø¹Ø¸ÙŠÙ… Ùˆ Ø£ØªÙˆØ¨Ù Ø¥Ù„ÙŠÙ‡ðŸ˜â¤.]]></document>
		<document><![CDATA[Ø¹ÙŠØ¯ Ù…ÙŠÙ„Ø§Ø¯ Ø§Ù„Ø§ÙˆØ²Ùˆ Ø­Ø¨ÙŠØ¨ Ø¹Ù…Ùˆ ðŸŽ‚ðŸŽ‚ðŸ˜ðŸ˜]]></document>
		<document><![CDATA[ÙˆØ¹Ø§ÙŠØ²Ù†Ø§ Ù†Ø±Ø¬Ø¹ Ø²ÙŠ Ø²Ù…Ø§Ù† .. Ù‚ÙˆÙ„ Ù„Ù„Ø²Ù…Ø§Ù† Ø§Ø±Ø¬Ø¹ ÙŠØ§Ø²Ù…Ø§Ù† ðŸ˜ðŸ˜€ðŸ˜€ https://t.co/HNKVxkJtJY]]></document>
		<document><![CDATA[Ø§Ù†Ø§ Ø¬ÙŠØª Ù„Ø§Ù‚ÙŠØª Ø§Ù…ÙŠ Ø¹Ø§Ù…Ù„Ø© ÙƒØ´Ø±Ù‰ ÙˆØ­Ø³ÙŠØª Ø§Ù†ÙŠ Ø¬Ø¹Ø§Ù† .. Ø§Ù†Ø§ ÙƒØ¯Ù‡ Ø·Ø¨ÙŠØ¹ÙŠ ØµØ­ØŸ ðŸ˜‚
 Ø£Ø­Ù…Ø¯ Ø®Ø§Ù„Ø¯ Ø­Ø³Ù†]]></document>
		<document><![CDATA[Ù‚Ù„ Ø§Ø¹ÙˆØ° Ø¨Ø±Ø¨ Ø§Ù„ÙÙ„Ù‚]]></document>
		<document><![CDATA[Ø´ÙƒØ±Ø§Ù‹ Ù„Ø§Ø®ÙˆØ§ØªÙ‰ Ø§Ù„Ù„Ù‰ Ø§Ø­ØªÙÙ„ÙˆØ§ Ø¨ÙŠØ§ Ø§Ù†Ù‡Ø§Ø±Ø¯Ø© Ø§Ø­Ù„Ù‰ Ù†Ø§Ø³ ÙˆØ±Ø¨Ù†Ø§ ÙÙ‰ #Ø¨Ù†Ùƒ_Ù…ØµØ± ÙƒÙ„Ù‡ .. ÙˆØ´ÙƒØ±Ø§Ù‹ Ù„ÙƒÙ„ Ø§Ù„Ù„Ù‰ Ø¨Ø¹ØªÙ„Ù‰ Ø±Ø³Ø§Ù„Ù‰ Ø§Ùˆ Ø¨ÙˆØ³Øª ..... https://t.co/dl82OxH9a7]]></document>
		<document><![CDATA[Ø§Ø­Ù„Ù‰ Ù†Ø§Ø³ ÙÙŠ #Ø¨Ù†Ùƒ_Ù…ØµØ± ðŸ˜ðŸ˜ðŸ˜]]></document>
		<document><![CDATA[Ø§Ù„Ù„Ù‰ Ø¹Ù…Ù„ Ø§Ù„ÙÙŠØ¯ÙŠÙˆ Ø¯Ù‡ Ù„Ø§Ø²Ù… ÙŠØªÙ‚ØªÙ„ ðŸ˜‚ðŸ˜‚ðŸ˜‚ðŸ˜‚ðŸ˜‚ðŸ˜‚ https://t.co/ywy3ObIURg]]></document>
		<document><![CDATA[Ù‚Ø§Ù„ÙˆØ§ Ø§ÙŠÙ‡ Ø¹Ù„ÙŠÙ†Ø§ .. Ù†Ø´ÙŠØ¯ Ø§Ù„ØµØ§Ø¹Ù‚Ø© â¤]]></document>
		<document><![CDATA[Ù‡Ùˆ ÙˆØ§Ø­Ø¯ Ø¨Ø³ Ø§Ù„Ù„ÙŠ Ø¨ÙŠØ³Ø¯ Ù…Ø¹Ø§ÙŠØ§ ÙÙŠ Ø§Ù„Ø§ÙƒÙ„ 
 Ø£Ø­Ù…Ø¯ Ø®Ø§Ù„Ø¯ Ø­Ø³Ù† ðŸ˜‚ðŸ˜‚ðŸ˜‚ https://t.co/U3WStYFIzg]]></document>
		<document><![CDATA[Ù…Ø·Ù„ÙˆØ¨ 100Ø¹Ø§Ù…Ù„ Ø¨Ø¯ÙˆÙ† Ø®Ø¨Ø±Ù‡ Ù„Ù„Ø¹Ù…Ù„ Ø¨Ø§Ù„Ù…ØªØ­Ù Ø§Ù„Ù…ØµØ±Ù‰ Ø§Ù„Ø¬Ø¯ÙŠØ¯ Ø¨Ù…Ø²Ø§ÙŠØ§ Ø§Ù„ØªØ¹ÙŠÙ† Ø§Ù„Ø­ÙƒÙˆÙ…Ù‰ Ø¨Ù…Ø±ØªØ¨ 2500Ø¬ ÙˆØ§Ù„Ù‚Ø¨Ø¶ ÙƒÙ„ Ø§Ø³Ø¨ÙˆØ¹ÙŠÙ† 1250Ø¬... https://t.co/mATfgk157n]]></document>
		<document><![CDATA[Ø§Ø±ÙƒØ¨ Ø§ÙŠÙ‡ Ù…Ù† Ø§Ù…Ø¨Ø§Ø¨Ø© Ù„Ø¬Ø²Ø± Ø§Ù„Ù…Ø§Ù„Ø¯ÙŠÙ ØŸ]]></document>
		<document><![CDATA[Ø§Ù„Ù„Ù‡Ù… ØªÙ‚Ø¨Ù„ Ø¯Ø¹Ø§Ø¦Ù†Ø§ ÙˆØªØ¬Ø§ÙˆØ² Ø¹Ù† Ø®Ø·Ø§ÙŠØ§Ù†Ø§ ..
Ù…ØªÙ†Ø³ÙˆØ´ Ø³ÙˆØ±Ù‡ Ø§Ù„ÙƒÙ‡Ù â¤ï¸]]></document>
		<document><![CDATA[Ø§Ù„Ù„Ù‡ ÙŠÙƒØ±Ù… Ø§ØµÙ„Ùƒ ÙŠØ§Ø¨Ù† Ø§Ù„Ù†Ø§Ø³ Ø§Ù„ÙƒÙˆÙŠØ³ÙŠÙ† .. Ø§ÙˆØ¬Ø²Øª Ù Ø§Ù†Ø¬Ø²Øª https://t.co/kNpfKAIJ5N]]></document>
		<document><![CDATA[Ø§ÙŠÙ…ÙˆØ´Ù† Ø­Ø§Ø·Ø· Ø±Ø¬Ù„ Ø¹Ù„Ù‰ Ø±Ø¬Ù„ ðŸ˜‚ðŸ˜‚ https://t.co/ai3J6QqgOS]]></document>
		<document><![CDATA[Ø§Ù†Ø§ Ù„Ùˆ Ù…Ù‚Ø¨Ø¶ØªØ´ Ø¨ÙƒØ±Ø© Ù‡Ø¨ÙŠØ¹ ÙƒÙ…Ø¨ÙŠÙˆØªØ± Ø§Ù„Ø´Ø±ÙƒØ© ðŸ˜ƒ]]></document>
		<document><![CDATA[Ø§ÙŠÙ‡ ÙŠØ§ÙˆÙ„Ø§Ø¯ Ø§Ù„ÙˆØ³Ø®Ù‡ ÙÙŠ Ø§ÙŠÙ‡ ðŸ˜‚ðŸ˜‚ðŸ˜‚ðŸ˜‚
Ø¯Ù‡ ØªØ§Ù†ÙŠ ÙÙŠØ¯ÙŠÙˆ Ø§Ù†Ù‡Ø§Ø±Ø¯Ø© https://t.co/pPIBbSwL9U]]></document>
		<document><![CDATA[Ø§ÙŠÙ‡ ÙŠØ§Ø¨Ù†Øª Ù‚Ù„Ø¨ÙŠ .. ÙŠØ§Ø¨Ù†Øª Ø¯ÙŠÙƒ Ø§Ù„Ø­Ø¨ ðŸ˜‚ðŸ˜‚ðŸ˜‚
Ahmed Saleh
Ù…ÙŠÙ†ÙØ¹Ø´ Ø§Ù„ÙÙŠØ¯ÙŠÙˆ Ø¯Ù‡ Ù…Ù† ØºÙŠØ±Ùƒ ðŸ˜‚ðŸ˜‚ðŸ˜‚ðŸ˜‚ðŸ˜‚ðŸ˜‚ https://t.co/evzicpGl7v]]></document>
		<document><![CDATA[ÙˆÙŽÙ…ÙŽØ§ ÙƒÙŽØ§Ù†ÙŽ Ù‚ÙŽÙˆÙ’Ù„ÙŽÙ‡ÙÙ…Ù’ Ø¥ÙÙ„ÙŽÙ‘Ø§ Ø£ÙŽÙ† Ù‚ÙŽØ§Ù„ÙÙˆØ§ Ø±ÙŽØ¨ÙŽÙ‘Ù†ÙŽØ§ Ø§ØºÙ’ÙÙØ±Ù’ Ù„ÙŽÙ†ÙŽØ§ Ø°ÙÙ†ÙÙˆØ¨ÙŽÙ†ÙŽØ§ ÙˆÙŽØ¥ÙØ³Ù’Ø±ÙŽØ§ÙÙŽÙ†ÙŽØ§ ÙÙÙŠ Ø£ÙŽÙ…Ù’Ø±ÙÙ†ÙŽØ§... https://t.co/AhixeqFpkI]]></document>
		<document><![CDATA[ØºÙŠØ« â¤
Ø§Ù„Ù„Ù‡Ù… Ø§Ø¹Ø·ÙŠÙ†Ø§ Ø®ÙŠØ±Ù‡ ÙˆØ§ÙƒÙÙŠÙ†Ø§ Ø´Ø±Ù‡]]></document>
		<document><![CDATA[Ø§Ù„Ù„Ù‡Ù… Ø¯Ø¨Ø± Ù„ÙŠ Ø£Ù…Ø±ÙŠ ÙØ£Ù†Ø§ Ù„Ø§ Ø§Ø­Ø³Ù† Ø§Ù„ØªØ¯Ø¨ÙŠØ±]]></document>
		<document><![CDATA[#Ø§Ù„Ø´Ø®Øµ_Ø§Ù„Ù…Ø²Ø§Ø¬ÙŠ 
*Ù…Ù…ÙƒÙ† Ø§Ù„Ø´Ø®Øµ Ø¯Ù‡ ÙŠØ´ÙˆÙ Ø±Ø³Ø§Ù„ØªÙƒ Ùˆ Ù…ÙŠØ±Ø¯Ø´ ÙÙŠ ÙˆÙ‚Øª Ù…Ø¹ÙŠÙ† Ù„Ø§Ù†Ù‡ ÙØ§Ù‚Ø¯ Ø§Ù„Ù‚Ø¯Ø±Ù‡ Ø§Ù†Ù‡ ÙŠØªÙˆØ§ØµÙ„ Ù…Ø¹ Ø§ÙŠ Ù…Ø®Ù„ÙˆÙ‚ Ù…Ø´ Ø­Ø¯... https://t.co/z50IgvMvKv]]></document>
		<document><![CDATA[Ø§ÙŠÙˆØ© Ù…Ø¨Ø­Ø¨Ø´ Ø§Ù„Ù…Ø´Ø§ÙƒÙ„ ÙˆØ¨Ø­Ø¨ Ø§Ù„Ù‡Ø¯ÙˆØ¡ .. Ù…Ø§Ù„Ø¯ÙŠÙ â¤ https://t.co/F2OrLZjxyn]]></document>
		<document><![CDATA[Ù„Ø§ Ù„Ø§ Ù„Ø§Ø¡ Ù„Ø§Ø¡ .. ØªØ¨Ù‚ÙŠ Ù…Ø¹Ø¯ÙŠÙ‡ Ù„Ø§Ø¡ Ù„Ø§Ø¡]]></document>
		<document><![CDATA[ØµÙ„ Ø¹Ù„Ù‰ Ø§Ù„Ù†Ø¨ÙŠ Ù…Ø­Ù…Ø¯ â¤ https://t.co/9ji36cGBcI]]></document>
		<document><![CDATA[Ù…Ø¨Ø­Ø¨Ø´ Ø§ØªÙƒÙ„Ù… Ø¹Ù†ÙŠ ÙƒØªÙŠØ± ðŸ˜‚ðŸ˜‚ðŸ˜‚ https://t.co/Dd7WCU7gCc]]></document>
		<document><![CDATA[ÙƒÙ„ Ø³Ù†Ø© ÙˆØ§Ù†ØªÙŠ Ø·ÙŠØ¨Ø© ÙŠØ§ Reem ðŸ˜¢ðŸ˜¢ðŸ˜¢ https://t.co/KOYiRRP3a0]]></document>
		<document><![CDATA[Ø§Ù„Ø­ÙˆØª â¤ https://t.co/hydVqkEhb6]]></document>
		<document><![CDATA[Ù…ÙŠØ²Ø© Ø§ÙˆÙ‚Ø§Øª Ø§Ù„Ø´Ø¯Ø© Ø§Ù†Ù‡Ø§ Ø¨ØªØºØ±Ø¨Ù„ Ø§Ù„Ù„Ù‰ Ø­ÙˆØ§Ù„ÙŠÙƒ
Ø¨ØªØ¹Ø±ÙÙƒ Ù…ÙŠÙ† Ù‡ÙŠÙØ¶Ù„ ÙˆØ§Ù‚Ù Ø¬Ù†Ø¨Ùƒ Ø¹Ù„Ù‰ Ø·ÙˆÙ„ ..
ÙˆØ¨ØªØ¹Ù„Ù…Ùƒ ØªØ­Ø· ÙƒÙ„ ÙˆØ§Ø­Ø¯ ÙÙ‰ Ù…ÙƒØ§Ù†Ù‡ Ø§Ù„ØµØ­ Ø§Ù„Ø­Ù‚ÙŠÙ‚Ù‰]]></document>
		<document><![CDATA[Ø§Ù„Ù†Ø§Ø³ Ø«Ù„Ø§Ø«Ø©
 Ø¹Ø§Ù„Ù… Ø±Ø¨Ø§Ù†ÙŠ ÙˆÙ…ØªØ¹Ù„Ù… Ø¹Ù„Ù‰ Ø³Ø¨ÙŠÙ„ Ù†Ø¬Ø§Ø© .. ÙˆÙ‡Ù…Ø¬ Ø±Ø¹Ø§Ø¹ ØºÙˆØºØ§Ø¡ Ø£ØªØ¨Ø§Ø¹ ÙƒÙ„ Ù†Ø§Ø¹Ù‚ .. ÙŠÙ…ÙŠÙ„ÙˆÙ† Ù…Ø¹ ÙƒÙ„ Ø±ÙŠØ­ .. Ù„Ù… ÙŠØ³ØªØ¶ÙŠØ¦ÙˆØ§... https://t.co/vQLeofdovX]]></document>
		<document><![CDATA[Ø¹Ù…ÙŠØªØ´ÙŠÙ† Ø§Ù‡Ù„Ùƒ ÙŠØ§ÙƒØ±Ø§Ù…Ù‰]]></document>
		<document><![CDATA[Ø¨Ø§Ù„Ù„ØºÙ‡ Ø§Ù„Ø¹Ø±Ø¨ÙŠØ© Ø§Ù„ÙØµØ­Ù‡ .. Ù…Ø¹ Ø§Ù„Ø§Ù‡Ù„Ù‰ Ø§Ø³ØªÙŠÙ‚Ø¸ ÙˆØ±ÙƒØ² ÙˆØ§ØµØ­ÙŠ]]></document>
		<document><![CDATA[Ø§Ù„Ø­Ù…Ø¯ Ù„Ù„Ù‡ https://t.co/97ykb4Nx8M]]></document>
		<document><![CDATA[Ø§Ù„ØµØ¯Ù‚Ø© Ù‡Ù‰ Ø§Ù„Ø­Ø§Ø¬Ù‡ Ø§Ù„ÙˆØ­ÙŠØ¯Ø© Ø§Ù„Ù„Ù‰ Ø·Ù„Ø¨ Ø§Ù„Ù…ÙŠØª Ø§Ù†Ù‡ ÙŠØ±Ø¬Ø¹ Ø§Ù„Ø­ÙŠØ§Ø© ØªØ§Ù†Ù‰ Ø¹Ø´Ø§Ù† ÙŠØ¹Ù…Ù„Ù‡Ø§ https://t.co/7hLMFxF3tF]]></document>
		<document><![CDATA["ÙŠØºÙØ± Ø§Ù„Ù„Ù‡ Ø°Ù†Ø¨Ùƒ ÙˆÙŠÙ‚Ø¶ÙŠ Ù‡Ù…Ù‘Ùƒ" 
 Ù‚Ø§Ù„Ù‡Ø§ Ø§Ù„Ù†Ø¨ÙŠ ï·º  Ù„Ù…Ù† Ø¬Ø¹Ù„ Ø¯Ø¹Ø§Ø¡Ù‡ ÙƒÙ„Ù‡ ØµÙ„Ø§Ø© Ø¹Ù„ÙŠÙ‡ØŒ ÙØ´ØºÙ„ØªÙ‡ Ù…Ø­Ø¨Ø© Ø§Ù„Ù†Ø¨ÙŠ ï·º Ø¹Ù† Ù†ÙØ³Ù‡ØŒ ÙÙƒØ§ÙØ£Ù‡... https://t.co/QvD78cpIGD]]></document>
		<document><![CDATA[Ø´ÙˆÙØªÙ‡ Ù„Ø­Ø¯ Ø¯Ù„ÙˆÙ‚ØªÙŠ 11 Ù…Ø±Ø© ðŸ˜‚ðŸ˜‚ðŸ˜‚ðŸ˜‚ðŸ˜‚ðŸ˜‚ðŸ˜‚ðŸ˜‚ðŸ˜‚ðŸ˜‚ðŸ˜‚ðŸ˜‚ðŸ˜‚ðŸ˜‚ðŸ˜‚ðŸ˜‚ðŸ˜‚ðŸ˜‚ðŸ‘ https://t.co/lLcMfK58zY]]></document>
		<document><![CDATA[Ø§Ù†Ø§ Ù‡ÙØ¶ÙŠ Ù„ÙƒÙˆØ§ Ø§Ù„Ø³Ø·ÙˆØ­ Ø¹Ù†Ø¯ÙŠ .. Ù‡Ø§ØªÙˆØ§ Ø§Ù„ÙˆØ§Ø¯ Ø­Ù…Ùˆ ÙˆØ§Ø·Ù„Ø¹Ùˆ .. Ù†ØºØªØµØ¨ÙˆØ§ ÙˆÙ†ØµÙˆØ±ÙˆØ§ ðŸ˜‚ðŸ˜‚ðŸ˜‚
Ramy Mahmoud]]></document>
		<document><![CDATA[Ø§Ø­Ù†Ø§ Ø§Ø³ÙŠØ§Ø¯ Ø§ÙØ±ÙŠÙ‚ÙŠØ§ ÙŠØ§Ø¨ÙˆØ§Ø¨ÙŠÙ† ÙŠØ§ÙˆÙ„Ø§Ø¯ Ø§Ù„ÙˆØ²Ù‡ ðŸ’ªðŸ’ªðŸ’ª]]></document>
		<document><![CDATA[Ø§Ø­Ù„Ù‰ ÙØ±Ø­Ù‡ Ø¯Ù‰ ÙˆÙ„Ø§ Ø§ÙŠÙ‡ ðŸ’ƒðŸ’ƒðŸ’ƒâ¤â¤â¤
#Ø§Ù„Ø§Ù‡Ù„Ù‰â¤â¤â¤]]></document>
		<document><![CDATA[Ø§ÙˆØ¹ÙŠ Ø§Ù„Ø¹Ù…Ø¯Ù‡ â¤â¤â¤]]></document>
		<document><![CDATA[ÙŠØ§Ø¬Ø¯Ø¹Ø§Ù† Ø§Ù„Ù„ÙŠ Ø¬Ù†Ø¨Ù‡ Ø²Ù…Ù„ÙƒØ§ÙˆÙ‰ ÙŠØ®Ù„ÙŠÙ‡ ÙŠØ±ÙˆØ­ .. ÙƒØ¯Ù‡ Ø­Ø±Ø§Ù… .. 6-1 

Ahmed Saleh ðŸ˜‚ðŸ˜‚ðŸ˜‚ðŸ˜‚]]></document>
		<document><![CDATA[ÙŠÙƒÙ†Ø´ Ø§Ù„Ø³Ø§Ø¯Ø³ Ø¬Ø§ÙŠ .. ÙˆÙŠØ®Ù„Øµ 6-1 ðŸ˜‚ðŸ˜‚ðŸ˜‚ðŸ˜‚ðŸ˜‚]]></document>
		<document><![CDATA[Ù„ÙŠÙ‡ Ù…ÙŠÙ†ÙƒØ¯Ø´ Ø¹Ù„Ù‰ Ø¯ÙŠÙƒ Ø§Ø¨ÙˆÙ†Ø§ .. Ø§Ø±Ø­Ù…Ù†Ø§ Ø¨Ù‚ÙŠ ÙŠØ§Ø¹Ù… Ø§ÙƒØ±Ø§Ù…Ù‰]]></document>
		<document><![CDATA[Ø§Ø­Ø§ Ø¨Ù‚ÙŠ .. Ù‡Ùˆ Ù„Ø§Ø²Ù… ÙŠØ¶Ø±Ø¨ Ø¹Ù„Ù‰ Ø¯Ù…Ø§ØºÙ‡ Ø¹Ø´Ø§Ù† ÙŠØ´ØªØºÙ„ .. Ø§ÙˆØ¹ÙŠ ÙŠØ¬ÙŠÙ„Ùƒ Ø§Ø²Ø§Ø±Ùˆ ðŸ˜‚ðŸ˜‚ðŸ˜‚â¤â¤]]></document>
		<document><![CDATA[Ø­Ø§Ø±Ø¨ Ø¹Ø§Ù„Ø¨Ø·ÙˆÙ„Ø© Ø¨Ø±ÙˆØ­ Ø§Ù„Ø§Ø¨Ø·Ø§Ù„
Ø¥Ù„Ù„Ø¹Ø¨ Ø¨ Ø±Ø¬ÙˆÙ„Ø© ØŒ Ù…ÙˆØª Ø¹ Ø§Ù„ÙƒÙˆØ±Ø© 
Ø§ÙØ±ÙŠÙ‚ÙŠØ§ Ù„Ù„ÙƒØ¨Ø§Ø± ÙˆØ§Ù†Øª Ø§Ù„Ø§Ø³Ø·ÙˆØ±Ø© ðŸ’ª

#Ø§ÙØ±ÙŠÙ‚ÙŠØ§_ÙŠØ§_Ø§Ù‡Ù„ÙŠ]]></document>
		<document><![CDATA[Ø§Ù„Ø­Ù…Ø¯ Ù„Ù„Ù‡ Ø¹Ù„Ù‰ Ù†Ø¹Ù…Ù‡ Ø§Ù„Ø§Ù‡Ù„Ù‰ â¤]]></document>
		<document><![CDATA[ÙˆÙ†Ø¨ÙŠ ÙŠØ§Ø¬Ø¯Ø¹Ø§Ù† Ø§Ù„Ù„Ù‰ Ø¬Ù†Ø¨Ù‡ Ø²Ù…Ù„ÙƒØ§ÙˆÙ‰ Ø¨ÙŠØªÙØ±Ø¬ ØºÙ…Ù‰ Ù„Ù‡ Ø¹ÙŠÙ†Ù‡ Ø¹Ø´Ø§Ù† Ø§Ù„Ù…Ø§ØªØ´ Ø¯Ù‡ Ù‚Ù„ÙŠÙ„ Ø§Ù„Ø§Ø¯Ø¨]]></document>
	</documents>
	</author>