<author lang="ar">
	<documents>
		<document><![CDATA[@amuralhajri Ø´Ø§Ø±Ø¹ Ù…Ù‡Ù… ÙƒØ°Ù„Ùƒ.

Ù†Ù†ØªØ¸Ø± Ø§ÙƒØªÙ…Ø§Ù„Ù‡.]]></document>
		<document><![CDATA[@omani8080h2014 Ù‡ÙŠ ÙˆØ§Ù„Ø¯Ø¹Ø§Ø¡ Ù…Ø§ Ù†Ù…Ù„Ùƒ!]]></document>
		<document><![CDATA[Ø³Ù„ÙƒØª Ø§Ù„ÙŠÙˆÙ… #Ø·Ø±ÙŠÙ‚_Ø§Ù„Ø¨Ø§Ø·Ù†Ø©_Ø§Ù„Ø³Ø±ÙŠØ¹
ÙˆÙ‚Ù„Øª ÙÙŠ Ù†ÙØ³ÙŠ:

Ø¬Ø²Ù‰ Ø§Ù„Ù„Ù‡ Ø®ÙŠØ±Ø§ ÙƒÙ„ Ù…Ù† ÙƒØ§Ù†Øª Ù„Ù‡ ÙŠØ¯ÙŒ ÙÙŠ ÙˆØ¬ÙˆØ¯ Ù‡Ø°Ø§ Ø§Ù„Ù…Ø´Ø±ÙˆØ¹ Ø§Ù„Ø­ÙŠÙˆÙŠ ÙˆØ§Ù„Ù…Ù‡Ù….

Ø¥Ù†Ù‘ Ø¨Ø¹Ø¶ Ø§Ù„Ø¥Ù†Ø¬Ø§Ø²Ø§Øª Ù„Ø§ ÙŠÙ…ÙƒÙ† ÙÙŠ Ù…ÙˆØ§Ø¬Ù‡ØªÙ‡Ø§ Ø³ÙˆÙ‰ Ø§Ù„Ø¯Ø¹Ø§Ø¡ØŒ ÙˆØ£Ù† Ù†Ù‚ÙˆÙ„:

Ø´ÙƒØ±Ø§.]]></document>
		<document><![CDATA[@i_sultan_r @kadwi69 Ù„ÙŠØªÙ†ÙŠ Ø£ØµÙ„ Ù„Ù„Ø®Ù…Ø³ Ø§Ù„Ø®Ø§Øµ Ø¨Ø§Ù„Ù…Ø¤Ù„ÙØ© Ù‚Ù„ÙˆØ¨Ù‡Ù….]]></document>
		<document><![CDATA[Ø§Ù„Ù†Ù‚Ø§Ø´ ÙÙŠ Ø·Ø±ÙŠÙ‚Ø© Ø¥Ø¯Ø§Ø±Ø© Ø§Ù„Ø£Ø³ØªØ§Ø° Ø®Ù…ÙŠØ³ Ù„Ø­Ø³Ø§Ø¨Ù‡ØŒ ÙŠØ­ØµØ± Ù…Ø§ Ø£Ø¹Ù†ÙŠÙ‡ ÙÙŠ ØªØºØ±ÙŠØ¯ØªÙŠ Ø§Ù„Ø³Ø§Ø¨Ù‚Ø© ÙÙŠ Ø²Ø§ÙˆÙŠØ© Ø¶ÙŠÙ‚Ø©.

ÙŠÙ‡Ù…Ù†ÙŠ Ø£Ù† Ø§Ù„Ø£Ø³ØªØ§Ø° Ø®Ù…ÙŠØ³ Ø¨Ø§Ø­Ø« ÙŠÙ…Ù„Ùƒ Ø±Ø¤ÙŠØ© ÙŠØ³Ø¹Ù‰ Ù…Ù†Ù‡Ø§ Ù„Ø³Ø¨Ø± Ø£ØºÙˆØ§Ø± ØªØ§Ø±ÙŠØ® Ø¹Ù…Ø§Ù†ØŒ ÙˆÙŠØ¨Ø¯Ù„ Ø¬Ù‡Ø¯Ø§ ÙÙŠ Ù…Ø¬Ø§Ù„Ø§Øª Ø«Ù‚Ø§ÙÙŠØ© Ù…ØªØ¹Ø¯Ø¯Ø©.

ÙˆÙŠØ³Ø§Ù‡Ù… ÙÙŠ Ù…Ø¬Ø§Ù„Ø§Øª Ø¹Ù„Ù…ÙŠØ© Ø³ØªØ¹ÙˆØ¯ Ø¹Ù„Ù‰ Ø¨Ù„Ø§Ø¯Ù†Ø§ Ø¨Ø§Ù„Ù†ÙØ¹.]]></document>
		<document><![CDATA[Ø£Ø¹Ø¬Ø¨ Ù…Ù† Ø£Ù†Ù‘ Ø¹Ø¯Ø¯ Ø§Ù„Ø°ÙŠÙ† ÙŠØªØ§Ø¨Ø¹ÙˆÙ†Ù†ÙŠ Ø£ÙƒØ¨Ø± Ù…Ù† Ø¹Ø¯Ø¯ Ø§Ù„Ø°ÙŠÙ† ÙŠØªØ§Ø¨Ø¹ÙˆÙ† Ù‡Ø°Ø§ Ø§Ù„Ø£Ø³ØªØ§Ø°: @kadwi69 

Ø£Ù‚ÙˆÙ„Ù‡Ø§ Ø¨ÙƒÙ„ Ø«Ù‚Ø©Ø› Ø³ØªØ®Ù„Ù‘Ø¯ Ø¹Ù…Ø§Ù† Ù‡Ø°Ø§ Ø§Ù„Ø§Ø³Ù…ØŒ ÙƒÙ…Ø§ Ø®Ù„Ø¯Øª Ù‚Ø¨Ù„Ù‡ Ø£Ø³Ù…Ø§Ø¡Ù‹ Ø­ÙØ±Øª ÙƒÙŠØ§Ù†Ù‡Ø§ ÙÙŠ Ø°Ø§ÙƒØ±Ø© Ø§Ù„ØªØ§Ø±ÙŠØ® Ø¨Ø£Ø­Ø±Ù Ù…Ù† Ø¶ÙŠØ§Ø¡.

ÙˆÙÙ‘Ù‚ Ø§Ù„Ù„Ù‡ Ø®Ù…ÙŠØ³ Ø§Ù„Ø¹Ø¯ÙˆÙŠ Ù„Ø®Ø¯Ù…Ø© Ø¹Ù…Ø§Ù† Ø¨ÙÙƒØ±Ù‡ Ø§Ù„Ù…Ø³ØªÙ†ÙŠØ± ÙˆÙ‡Ù…ØªÙ‡ Ø§Ù„Ø¹Ø§Ù„ÙŠØ©ØŒ ÙˆØ£Ù…Ø¯Ù‡ Ø¨Ø§Ù„ØµØ­Ø© ÙˆØ§Ù„ØªÙˆÙÙŠÙ‚ ÙˆØ§Ù„Ø³Ø¯Ø§Ø¯.]]></document>
		<document><![CDATA[@alqaidi_a @hope93333 @ikhulood9 Ø§Ù„Ø®Ù„Ø¹ Ø¨Ù…Ù‚Ø§Ø¨Ù„ ÙˆØ¨Ø¥Ø±Ø§Ø¯Ø© Ø§Ù„Ø·Ø±ÙÙŠÙ†ØŒ ÙˆÙ‡Ø°Ø§ Ø¨Ø¥Ø±Ø§Ø¯Ø© Ù…Ù†ÙØ±Ø¯Ø© ÙˆØ¨Ø¯ÙˆÙ† Ù…Ù‚Ø§Ø¨Ù„ ðŸ˜]]></document>
		<document><![CDATA[@AliAbuali01010 @hope93333 @ikhulood9 Ù„Ùˆ Ø§Ø´ØªØ±Ø·ØªÙ‡ Ø§Ù„Ù…Ø±Ø£Ø© Ù‚Ø¨Ù„ Ø§Ù„Ø¹Ù‚Ø¯ Ù„ÙƒØ§Ù† Ù„Ù‡Ø§ Ø°Ù„Ùƒ.
Ø§Ù„Ù„Ù‡ ÙŠÙ‡Ø¯ÙŠÙƒ ØªØ®Ù„ÙŠÙ†Ø§ Ù†Ø¹Ù„Ù…Ù‡Ù… ÙˆØ¨Ø¹Ø¯ÙŠÙ† ÙŠØ´ÙˆØªÙˆÙ†Ø§ ðŸ˜]]></document>
		<document><![CDATA[@AliAbuali01010 @hope93333 @ikhulood9 Ø·Ù„Ù‚Øª Ù†ÙØ³ÙŠ Ù…Ù†Ùƒ.]]></document>
		<document><![CDATA[@hope93333 @ikhulood9 Ø¥Ø°Ø§ Ø§Ø´ØªØ±Ø·Øª Ø§Ù„Ø²ÙˆØ¬Ø© Ø£Ù† ØªÙƒÙˆÙ† Ø¹ØµÙ…Ø© Ø§Ù„Ù†ÙƒØ§Ø­ Ø¨ÙŠØ¯Ù‡Ø§.]]></document>
		<document><![CDATA[@0Omani Ù…ÙˆØ¯ØªÙŠ ðŸ™ðŸ»]]></document>
		<document><![CDATA[Ù‚Ø§Ù„Øª Ø§Ù„Ù†Ø®ÙŠÙ„ Ù„Ø£Ø¬Ø¯Ø§Ø¯Ù†Ø§ Ø§Ù„Ù‚Ø¯Ù…Ø§Ø¡ Ø­ÙƒÙ…Ø© Ø¨Ø§Ù„ØºØ©ØŒ Ø­ÙŠÙ† Ø¹Ù„Ù‘Ù…ØªÙ‡Ù… ÙƒÙŠÙ ÙŠÙƒÙˆÙ†ÙˆÙ† Ø´ÙˆÙƒØ©Ù‹ ØªÙÙ‚Ø£ Ø£Ø¹ÙŠÙ† Ø§Ù„Ø£Ø¹Ø¯Ø§Ø¡.
ÙˆÙ‚Ø¯ Ù‡Ù…Ø³Øª Ø§Ù„Ø¬Ø¨Ø§Ù„ Ø£ÙŠØ¶Ø§ Ù„Ù‡Ù… Ø¨Ø³Ø±ÙÙ‘ Ø¯ÙÙŠÙ†Ø› Ø¹Ù†Ø¯Ù…Ø§ Ø£Ø®Ø¨Ø±ØªÙ‡Ù… ÙƒÙŠÙ ÙŠÙƒÙˆÙ† Ø§Ù„Ø§Ø±ØªÙ‚Ø§Ø¡ Ø¹Ù† Ø§Ù„ØµØºØ§Ø¦Ø±.
ÙˆÙ…Ù†Ø° Ø¹ØµÙˆØ± ØºØ§Ø¨Ø±Ø©ØŒ ÙˆÙ‚ÙˆÙ‰ Ø§Ù„Ø¨ØºÙŠ ØªØªÙ‚Ø²Ù… Ø£Ù…Ø§Ù… Ø´Ù…ÙˆØ® Ø£Ù‡Ù„ Ù‡Ø°Ù‡ Ø§Ù„Ø£Ø±Ø¶ØŒ  ÙˆØªÙ†Ø¯Ø­Ø± ØµØ§ØºØ±Ø© Ø£Ù…Ø§Ù… Ø´ÙˆÙƒØªÙ‡Ù….]]></document>
		<document><![CDATA[@y2KrAPncXe3SppJ @kadwi69 @almajma3 Ù…Ø§ Ø²Ø§Ù„ÙˆØ§ ÙÙŠ Ù‚Ø±ÙŠØªÙ†Ø§ ÙŠÙ‚ÙˆÙ„ÙˆÙ† Ù„Ù…Ù† ÙŠØ¹Ù…Ù„ ÙÙŠ Ø§Ù„Ø²Ø±Ø§Ø¹Ø© Ù…Ø«Ù„Ø§:
Ù…ÙˆÙ‡ ØªØ¹Ø§Ø¨Ù„ÙˆØ§.
ÙˆÙ„Ù…Ù† Ø·Ù„Ø¨Øª Ù…Ù†Ù‡ Ù…Ø³Ø§Ø¹Ø¯Ø© ÙÙ‚Ø§Ù… Ø¨Ù‡Ø§:
Ø¹Ø¨Ù„Ù†Ø§Ùƒ.]]></document>
		<document><![CDATA[@hUEOlj77iiK0ilQ @OmanEliteGroup @amal55553 ÙØ¹Ù„Ø§.
Ù‚Ø±Ø£Øª Ù‡Ø°Ù‡ Ø§Ù„Ù…Ø¹Ù„ÙˆÙ…Ø© Ø£ÙŠØ¶Ø§.
ÙˆÙ„ÙƒÙ† Ø§Ù„ÙÙƒØ±Ø© Ø¹Ù†Ø¯Ù…Ø§ ØªØªØºÙ„ØºÙ„ ÙÙŠ Ø§Ù„Ø¹Ù‚ÙˆÙ„ ØªØµØ¨Ø­ Ù…Ø§Ù„ÙƒØ© Ù„ØµØ§Ø­Ø¨Ù‡Ø§.]]></document>
		<document><![CDATA[@jsyabi @37Kp71dGnvgxi7M @maimunAsulimani Ø§Ù„Ù…Ø¹Ø±ÙˆÙ ÙŠØ¤Ø®Ø° ÙˆÙŠØ¹Ø·Ù‰ Ø¨ÙŠÙ† Ø§Ù„Ù†Ø§Ø³.]]></document>
		<document><![CDATA[@jsyabi @37Kp71dGnvgxi7M @maimunAsulimani Ø£Ø³ØªØ§Ø¯Ø© Ù…ÙŠÙ…ÙˆÙ†Ø©
ÙƒÙ…Ù„ÙŠ Ù…Ø¹Ø±ÙˆÙÙƒ.
ðŸ™ˆ]]></document>
		<document><![CDATA[@jsyabi @37Kp71dGnvgxi7M @maimunAsulimani Ø§Ù†ØªÙ‡ Ù…Ù† Ø§Ø³Ù…Ùƒ Ù…Ø´Ø§ÙƒØ³
Ø¯ÙˆØ§Ùƒ ðŸ˜]]></document>
		<document><![CDATA[@maimunAsulimani @alomaniya @37Kp71dGnvgxi7M ÙŠÙ…Ø²Ø­ÙˆØ§ Ø£Ø³ØªØ§Ø°Ø©
Ø®Ù„Ùƒ Ù…Ø«Ù„ÙŠ ÙˆØ§Ø¶Ø­ÙƒÙŠ ÙƒØ°Ø§ ðŸ¤£]]></document>
		<document><![CDATA[@alomaniya @maimunAsulimani @37Kp71dGnvgxi7M Ø´ÙØª ÙƒÙŠÙ ðŸ˜]]></document>
		<document><![CDATA[@maimunAsulimani @37Kp71dGnvgxi7M ÙƒÙÙˆ ÙˆØ§Ù„Ù„Ù‡.
ØªØ³Ù„Ù…ÙŠ ÙŠØ§ Ø±Ø§Ø¦Ø¹Ø©.]]></document>
		<document><![CDATA[@37Kp71dGnvgxi7M @maimunAsulimani Ù„Ùˆ Ù…Ø§ Ù…ØªØ¨Ù„Ø¹Ø³ Ù…Ø§ Ø£ØªØ­Ø¸Ø±Ùƒ ðŸ˜
Ø£Ø³ØªØ§Ø°Ø© Ø·Ø§Ù„Ø¨Ù†Ùƒ ØªØ±ÙØ¹ÙŠ Ø¹Ù†Ù‡ Ø§Ù„Ø­Ø¸Ø±]]></document>
		<document><![CDATA[@faham20121 Ø§Ù„ØªÙˆÙ„Ø© Ø¨ÙƒÙ…ØŸ]]></document>
		<document><![CDATA[@AliAbuali01010 Ù„Ù… Ø£Ø³Ø£Ù„ Ø¹Ù† Ø§Ù„Ø·Ø±ÙŠÙ‚!
Ø¹Ù…ÙˆÙ…Ø§ ÙƒÙ†Øª Ø·Ø§Ù…Ø¹Ø§ ÙÙŠ Ø§Ù„Ø­ØµÙˆÙ„ Ø¹Ù„Ù‰ Ù…ÙÙ‡ÙˆÙ… Ø§Ù„Ù…Ø¹Ø±ÙØ© Ù„Ø¯ÙŠÙƒ Ù„Ø§ Ø£ÙƒØ«Ø±.
Ø´ÙƒØ±Ø§ ðŸ‘‹]]></document>
		<document><![CDATA[@AliAbuali01010 Ø£ÙŠÙ† ØªØ¹Ø±ÙŠÙÙ‡Ø§ Ù‡Ù†Ø§ØŸ]]></document>
		<document><![CDATA[@Omanlady3 @bint_qaboos2 ÙˆÙ„ÙƒÙ†Ù‡Ø§ Ù…ÙˆØ¬ÙˆØ¯Ø©.]]></document>
		<document><![CDATA[@AliAbuali01010 ÙƒØ§Ù†Øª Ù…Ø§Ø°Ø§ØŸ]]></document>
		<document><![CDATA[Ø§Ù„Ù…Ø¹Ø±ÙØ© Ù‡ÙŠ ØªÙ„Ùƒ Ø§Ù„Ù‚Ù†Ø§Ø¹Ø©ØŒ Ø§Ù„ØªÙŠ ÙŠØ¬Ø¯Ù‡Ø§ Ø§Ù„Ø¹Ø§Ù„ÙÙ… ÙÙŠ Ù†Ù‚Øµ Ø¹Ù„Ù…Ù‡ØŒ ÙˆÙŠØ¬Ø¯Ù‡Ø§ Ø§Ù„Ø¬Ø§Ù‡Ù„ ÙÙŠ Ø²ÙŠØ§Ø¯Ø© Ø¬Ù‡Ù„Ù‡.]]></document>
		<document><![CDATA[@bint_qaboos2 Ù„Ø§ ÙŠØ³Ù„Ù…Ù Ø§Ù„Ø¥Ù†Ø³Ø§Ù† Ù…Ù† Ø¶Ø¯Ù ÙˆÙ„Ùˆ
Ø­Ø§ÙˆÙ„ Ø§Ù„Ø¹Ø²Ù„Ø© ÙÙŠ Ø±Ø£Ø³ Ø¬Ø¨Ù„.

ÙˆÙ„Ø°Ù„ÙƒØ› Ù†Ø±Ù‰ Ø§Ù„Ø¹Ø¯Ø§ÙˆØ© Ø§Ù„Ø¢Ù†ØŒ ÙˆÙ„Ø§ Ù†Ø±Ù‰ Ø£Ø³Ø¨Ø§Ø¨Ù‡Ø§ â—ï¸]]></document>
		<document><![CDATA[Ø§Ù„Ø­Ù‚ÙŠÙ‚Ø© Ù‡ÙŠ Ù…Ø§ ÙˆØ§ÙÙ‚Øª Ø§Ù„ÙˆØ§Ù‚Ø¹ØŒ ÙˆÙˆØ§Ù‚Ø¹Ù†Ø§ Ø¨Ù‡ ÙƒØ«ÙŠØ± Ù…Ù† Ø§Ù„ÙˆÙ‡Ù…. https://t.co/8pySyk2UxO]]></document>
		<document><![CDATA[@unizwaoman Ø¬Ù‡Ø¯ Ù…Ø´ÙƒÙˆØ±.
Ù„ÙƒÙ† Ø§Ù„ØªÙˆÙÙŠÙ‚ Ø£Ù…Ù†ÙŠØ© ÙˆØ¯Ø¹Ø§Ø¡.]]></document>
		<document><![CDATA[@unizwaoman Ø§Ù„Ø¥Ø¹Ù„Ø§Ù† ÙŠØ®Ù„Ùˆ Ù…Ù† Ø§Ù„ØªÙˆÙ‚ÙŠØª!]]></document>
		<document><![CDATA[@alsaim_ Ø±Ø­Ù…Ù‡ Ø§Ù„Ù„Ù‡
ØªÙ„Ùƒ Ø±Ø¤ÙŠØªÙ‡Ù… ÙˆÙ„Ù‡Ù… Ø§Ù„Ø£Ø¬Ø± ðŸ˜]]></document>
		<document><![CDATA[@Yousuf_Alhooti1 Ø¹ Ø§Ù„Ø¢Ø®Ø± ðŸ™ˆ]]></document>
		<document><![CDATA[@alsalmiibrahim Ø£Ø­ÙƒÙŠÙ„Ùƒ Ø§Ù„Ø³Ø§Ù„ÙØ© Ù…Ù† Ø·Ø£Ø·Ø£ Ù„Ø³Ù„Ø§Ù… Ø¹Ù„ÙŠÙƒÙˆ ÙˆØ§ÙƒØªØ¨ ðŸ˜]]></document>
		<document><![CDATA[@BuNasser1963 Ù…Ø´ØªØ§Ù‚ÙŠÙ†Ùƒ Ø¹ÙŠÙ†ÙŠ]]></document>
		<document><![CDATA[@muhanna_darmaki @abnbarka Ø¹Ø¬ÙŠØ¨ðŸ‘]]></document>
		<document><![CDATA[@muhanna_darmaki @abnbarka Ø£Ø³ØªØ§Ø° Ù…Ù‡Ù†Ø§ Ø§ÙŠØ´ Ù†ÙˆØ¹ Ø§Ù„ØªÙ„ÙÙˆÙ†ØŸ
Ø³Ø£Ù„Øª Ù„Ø£Ù†Ù‡ Ù…Ø·Ù„Ø¹Ù†Ø§ Ø­Ù„ÙˆÙŠÙ† ðŸ˜‰]]></document>
		<document><![CDATA[@hakeemo_89 Ø®Ù„ÙŠ Ø¹Ù†Ùƒ ðŸ˜]]></document>
		<document><![CDATA[@imalik97 Ø§Ù„Ù„Ù‡ Ø³ØªØ± ðŸ˜]]></document>
		<document><![CDATA[@shaqsi_al Ø­Ø¸ÙŠ Ø£Ù†Ù‡Ø§ ÙƒØ§Ù†Øª Ø§Ù…Ø±Ø£Ø© Ù…Ù‡Ø°Ø¨Ø©
ÙˆÙ„Ø§ ÙƒÙ†Øª Ø­ØµÙ„Øª Ù‚Ø´Ø§Ø¨ ØºØ§ÙˆÙŠ ðŸ˜]]></document>
		<document><![CDATA[@warmth18_ Ù…Ù† Ù‚Ø§Ù„ ðŸ˜³
Ù…Ù† Ø¥Ø­Ø±Ø§Ø¬Ø§Øª Ø§Ù„Ø¯Ù†ÙŠØ§ ðŸ™ˆ]]></document>
		<document><![CDATA[@ASSM1323 Ù„Ø§ ØªÙˆÙ‚ÙÙ‡ Ø¹Ù† Ø§Ù„Ø¶Ø±Ø¨ ðŸ˜]]></document>
		<document><![CDATA[@LogisticsOman Ù„Ùˆ ÙÙˆØ§Ø¯ÙŠ Ù…Ø¹Ù‡Ø§ ÙƒÙ†Øª Ø£Ø´ÙˆÙÙ‡Ø§ Ù‚Ø¨Ù„.
ðŸ™ˆ]]></document>
		<document><![CDATA[@ASSM1323 Ø¨Ø§Ù„ØºÙ„Ø· ðŸ™ˆ]]></document>
		<document><![CDATA[Ø¨ÙŠÙ†Ù…Ø§ ÙƒÙ†Øª Ù…Ù†Ø´ØºÙ„Ø§ Ø¨ÙƒØªØ§Ø¨Ø© ØªØºØ±ÙŠØ¯Ø§Øª Ø§Ù„Ø£Ù…Ø³ØŒ Ø¬Ù„Ø³Øª ÙÙŠ Ø§Ù„ÙƒØ±Ø³ÙŠ Ø§Ù„Ù…ÙˆØ§Ø¬Ù‡ Ù„Ù‡Ø§ ÙÙŠ Ø§Ù„Ù…Ù‚Ù‡Ù‰ØŒ ÙˆØ¹Ù†Ø¯Ù…Ø§ Ø£ÙƒÙ…Ù„Øª ÙƒØªØ§Ø¨Ø© Ø§Ù„ØªØºØ±ÙŠØ¯Ø© ÙˆØ±ÙØ¹Øª Ø±Ø£Ø³ÙŠØŒ ØªÙØ§Ø¬Ø£Øª Ø¨Ø£Ù†Ù‡Ø§ Ø§Ù…Ø±Ø£Ø© Ø£Ø®Ø±Ù‰ØŒ ÙØ§Ù†ØªÙØ¶Øª ÙˆØ§Ù‚ÙØ§ØŒ ÙˆØ¨ÙƒÙ„ Ø§Ø±ØªØ¨Ø§ÙƒØŒ Ù‚Ù„Øª Ù„Ù‡Ø§: Ø¢Ø³ÙØŒ ÙˆÙ…Ø´ÙŠØª ÙˆØ£Ù†Ø§ ÙƒÙ…Ø§ ÙŠÙ‚ÙˆÙ„ÙˆÙ† Ø¹Ù†Ø¯Ù†Ø§: "Ù…Ø§ ÙÙŠÙŠ Ù‚Ø·Ø±Ø© Ø¯Ù…".
#Ù…ÙˆÙ‚Ù_Ù„Ø§_ÙŠÙÙ†Ø³Ù‰]]></document>
		<document><![CDATA[@KAlsuleimani @mohad_hinai @AJArabic Ù‡ÙŠÙ‡ ÙˆØ§Ù„Ù„Ù‡.
Ø£ÙØ¶Ù„ Ù…ÙˆØ¸Ù ÙÙŠ Ø§Ù„Ø®Ø·.]]></document>
		<document><![CDATA[@mohad_hinai @AJArabic ÙƒØ§Ù† Ø£ÙƒØ«Ø± ÙˆØ§Ø­Ø¯ Ù…Ø·ÙØ±Ø¨ÙŠ Ù„Ù…Ø§ ÙƒÙ†Øª Ø±Ø¦ÙŠØ³ Ù„Ù…Ø­ÙƒÙ…Ø© Ù†Ø²ÙˆÙ‰.
ÙˆØ±ØºÙ… Ø°Ù„Ùƒ ÙŠÙ†Ø­Ø¨ ðŸ˜]]></document>
		<document><![CDATA[@abduh4998 Ø¬Ù…ÙŠÙ„ ðŸ˜]]></document>
		<document><![CDATA[@iAhmedios Ù…Ù† Ù„Ù… ÙŠØ¹Ø±Ù Ø§Ù„Ø£Ø³Ø¨Ø§Ø¨ Ø§Ù„Ù‚Ø§Ø¦Ù…Ø© Ø­Ø§Ù„ÙŠØ§ ÙÙ„ÙŠØ¹Ø¯ Ø§Ù„Ù†Ø¸Ø±!]]></document>
		<document><![CDATA[@fatmaomani @ahmedgrnas9145 Ø´ÙƒØ±Ø§.]]></document>
		<document><![CDATA[@ahmedgrnas9145 @fatmaomani Ø¨Ø¥Ø°Ù† Ø§Ù„Ù„Ù‡]]></document>
		<document><![CDATA[@Yaqoobalharthy Ø³ÙˆÙ Ù†ØªØ¬Ø§ÙˆØ² ÙƒÙ„ Ø°Ù„Ùƒ Ø¨Ø¥Ø°Ù† Ø§Ù„Ù„Ù‡.]]></document>
		<document><![CDATA[8
Ù…Ø¤Ø¯Ù‰ Ø°Ù„Ùƒ Ø¶Ø±ÙˆØ±Ø© Ø§Ù„Ø§ØªÙØ§Ù‚ Ø¹Ù„Ù‰ Ø£Ù†Ù‘ Ù…Ø¹Ø±ÙØ© Ø§Ù„ÙˆØ§Ù‚Ø¹ Ù…Ù† Ø§Ù„Ø£Ù‡Ù…ÙŠØ© Ø¨Ù…ÙƒØ§Ù† Ø£Ù† ØªØªÙ… Ù…Ø±Ø§Ø¹Ø§ØªÙ‡Ø§ Ø¹Ù†Ø¯ Ø§Ù„Ù‚ÙŠØ§Ù… Ø¨Ø£ÙŠ Ø±Ø¯Ø§Øª ÙØ¹Ù„ØŒ Ù…Ø¹ Ø§Ù„ØªØ³Ù„ÙŠÙ… Ø¨Ø£Ù† Ø¬Ø²Ø¡Ø§Ù‹ Ù…Ù† Ø§Ù„ØªÙØ§ØµÙŠÙ„ Ø§Ù„Ù…Ù‡Ù…Ø© Ù„Ø§ ÙŠÙ…ÙƒÙ† Ø£Ù† ØªÙØ¹Ù„Ù† Ù„Ù„ÙƒØ§ÙØ©ØŒ Ù„Ù…Ø§ ÙÙŠ Ø°Ù„Ùƒ Ù…Ù† Ø£Ø¶Ø±Ø§Ø± Ù‚Ø¯ ØªØªØ±ØªØ¨ Ø¹Ù„Ù‰ Ø£ØµØ¹Ø¯Ø© Ù…Ø®ØªÙ„ÙØ©Ø› Ø³ÙˆØ§Ø¡ Ø£ÙƒØ§Ù†Øª Ø£Ù…Ù†ÙŠØ© Ø£Ù… Ø§Ù‚ØªØµØ§Ø¯ÙŠØ© Ø£Ù… Ø³ÙŠØ§Ø³ÙŠØ© Ø£Ù… Ø§Ø¬ØªÙ…Ø§Ø¹ÙŠØ©.]]></document>
		<document><![CDATA[7
ÙƒØ°Ù„Ùƒ ÙØ¥Ù† Ø§Ù„Ù…Ø¨Ø§Ø­Ø§Øª Ù…Ù† Ø§Ù„Ø£Ù…ÙˆØ± ÙÙŠ Ù…Ø±Ø§Ø­Ù„ Ø³Ø§Ø¨Ù‚Ø©ØŒ Ù‚Ø¯ ØªÙ‚ØªØ¶ÙŠ Ù…Ø±Ø­Ù„Ø© Ù…Ù† Ø§Ù„Ù…Ø±Ø§Ø­Ù„ Ù…Ù†Ø¹ Ø¨Ø¹Ø¶Ù‡Ø§ØŒ ÙˆØ°Ù„Ùƒ Ù„Ø§Ø¹ØªØ¨Ø§Ø±Ø§Øª Ø®Ø§ØµØ© ØªØ¬Ø¹Ù„ Ù…Ù† Ø§Ø­ØªÙ…Ø§Ù„ÙŠØ© Ø£Ù† ØªØªØ¹Ø¯Ù‰ ØªÙ„Ùƒ Ø§Ù„Ù…Ø¨Ø§Ø­Ø§Øª Ù„ØªØ´ÙƒÙ„ ØªÙ…Ù‡ÙŠØ¯Ø§Ù‹ Ù„Ù†ØªØ§Ø¦Ø¬ Ø®Ø·ÙŠØ±Ø©ØŒ Ø®Ø§ØµØ© ÙÙŠ Ø§Ù„Ø£Ù…ÙˆØ± Ø°Ø§Øª Ø§Ù„ØªÙˆØ¬Ù‡Ø§Øª Ø§Ù„Ø¹Ø§Ù…Ø©ØŒ Ø§Ù„ØªÙŠ ÙŠÙ…ÙƒÙ† Ø£Ù† ØªØ³ØªØ­ÙŠÙ„ Ø§Ù„Ø³ÙŠØ·Ø±Ø© Ø¹Ù„ÙŠÙ‡Ø§ Ø¥Ø°Ø§ Ø§Ù†ÙÙ„ØªØª Ø¹Ù† Ø§Ù„ØµÙˆØ±Ø© Ø§Ù„ØªÙŠ Ø¨Ø¯Ø£Øª Ø¨Ù‡Ø§.]]></document>
		<document><![CDATA[6
ÙŠØ­Ø¯Ø« ÙÙŠ Ù…Ø«Ù„ Ù‡Ø°Ù‡ Ø§Ù„Ø­Ø§Ù„Ø© Ù‚ÙŠØ§Ù… Ø§Ù„Ø£ØºÙ„Ø¨ÙŠØ© Ø¨Ø§Ø³ØªØ­Ø¶Ø§Ø± Ø§Ù„Ù…Ù‚Ø§Ø±Ù†Ø§ØªØŒ ÙˆÙ…Ù†Ø§Ù‚Ø´Ø© Ø§Ù„Ø£Ø®Ø·Ø§Ø¡ Ø§Ù„Ø³Ø§Ø¨Ù‚Ø©ØŒ ÙˆÙ…Ø¹ Ø¹Ø¯Ù… Ø¥Ù…ÙƒØ§Ù† Ù†ÙÙŠ Ø­Ø¯ÙˆØ« Ø£Ø®Ø·Ø§Ø¡ØŒ Ø£Ùˆ Ø§Ù„Ù‚ÙˆÙ„ Ø¨Ø¹Ø¯Ù… Ù‚Ø¨ÙˆÙ„ Ø§Ù„Ù…Ù‚Ø§Ø±Ù†Ø§Øª ÙÙŠ Ø¨Ø¹Ø¶ Ø§Ù„Ù…Ø³Ø§Ø¦Ù„ØŒ Ø¥Ù„Ø§ Ø¥Ù†Ù‡ ÙˆØ¨Ø§Ù„Ø±ØºÙ… Ø°Ù„Ùƒ Ù„Ø§ ÙŠÙ…ÙƒÙ† Ø§Ù„ØªØ°Ø±Ø¹ Ø¨Ù‡Ø°Ù‡ Ø§Ù„Ø£Ø³Ø¨Ø§Ø¨ Ù„ØªØ¬Ø§Ù‡Ù„ Ø§Ù„Ø£Ø®Ø° Ø¨Ø§Ù„ØªØµØ±Ù Ø§Ù„Ù…Ù†Ø§Ø³Ø¨ Ù„Ù„Ù…Ø±Ø­Ù„Ø© Ø¨Ù…Ø§ ØªÙ…Ù„ÙŠÙ‡ Ø¸Ø±ÙˆÙÙ‡Ø§ØŒ ÙˆØªÙØ±Ø¶Ù‡ Ø§Ø¹ØªØ¨Ø§Ø±Ø§ØªÙ‡Ø§.]]></document>
		<document><![CDATA[5
Ù‚Ø¯ ØªÙ…ØªÙ†Ø¹ Ø§Ù„Ø¯ÙˆÙ„Ø© Ø¹Ù† Ù…Ù†Ø­ Ø¨Ø¹Ø¶ Ø§Ù„Ø§Ù…ØªÙŠØ§Ø²Ø§Øª Ø£Ùˆ Ø§Ù„ÙˆÙØ§Ø¡ Ø¨Ø¨Ø¹Ø¶ Ø§Ù„Ø­Ù‚ÙˆÙ‚ØŒ ÙÙŠ Ù…Ø±Ø­Ù„Ø© Ù…Ù† Ø§Ù„Ù…Ø±Ø§Ø­Ù„ØŒ Ù„ÙŠØ³ Ù†ÙƒØ±Ø§Ù†Ø§Ù‹ Ù„ØªÙ„Ùƒ Ø§Ù„Ø­Ù‚ÙˆÙ‚ØŒ ÙˆØ¥Ù†Ù…Ø§ Ø¨Ø³Ø¨Ø¨ Ø¸Ø±ÙˆÙ ØªÙ…Ø± Ø¨Ù‡Ø§ØŒ ØªØ¬Ø¹Ù„ Ù…Ù† Ø§Ù„ÙˆÙØ§Ø¡ Ø¨ØªÙ„Ùƒ Ø§Ù„Ø­Ù‚ÙˆÙ‚ Ø£Ùˆ Ø§Ù„Ø§Ù„ØªØ²Ø§Ù…Ø§Øª Ù…ØºØ§Ù…Ø±Ø©ØŒ ÙŠÙ…ÙƒÙ† Ø£Ù† ØªÙ‚ÙˆØ¯ Ù„Ø£Ø¶Ø±Ø§Ø± Ø£ÙƒØ¨Ø± Ø¹Ù„Ù‰ Ø§Ù„ØµØ¹ÙŠØ¯ Ø§Ù„Ø¹Ø§Ù… Ù„Ù„Ù…ØµÙ„Ø­Ø© Ø§Ù„ÙˆØ·Ù†ÙŠØ© Ø§Ù„Ø¹Ù„ÙŠØ§.]]></document>
		<document><![CDATA[4
Ø§Ù„Ù…Ù†ÙØ¹Ø© Ù„Ø§ Ø¨Ø¯ Ø£Ù† ØªÙØ­Ø³Ø¨ Ù…Ø¹ Ø­Ø³Ø§Ø¨ Ø§Ù„Ø¶Ø±Ø± ÙÙŠ ÙƒÙ„ Ø£Ù…Ø± ÙŠÙ‚ÙˆÙ… Ø§Ù„Ø¥Ù†Ø³Ø§Ù† Ø¨Ù‡ØŒ Ù‡Ø°Ø§ Ø¹Ù„Ù‰ Ø§Ù„ØµØ¹ÙŠØ¯ Ø§Ù„Ø´Ø®ØµÙŠ. Ø£Ù…Ø§ Ø¹Ù„Ù‰ Ø§Ù„ØµØ¹ÙŠØ¯ Ø§Ù„Ø¹Ø§Ù… ÙØ¥Ù†Ù‘ Ù‡Ø°Ø§ Ø§Ù„Ø­Ø³Ø§Ø¨ Ø¨Ø­Ø§Ø¬Ø© Ø¥Ù„Ù‰ Ø£Ù† ÙŠÙƒÙˆÙ† Ø£ÙƒØ«Ø± Ø¯Ù‚Ø©ØŒ ÙˆØ£Ø¨Ù„Øº Ø­Ø°Ø±Ø§ØŒ Ù…Ø¹ Ø§Ù„Ø£Ø®Ø° ÙÙŠ Ø§Ù„Ø§Ø¹ØªØ¨Ø§Ø±  Ø£Ù† "Ø¯Ø±Ø¡ Ø§Ù„Ù…ÙØ§Ø³Ø¯ Ù…Ù‚Ø¯Ù… Ø¹Ù„Ù‰ Ø¬Ù„Ø¨ Ø§Ù„Ù…ØµØ§Ù„Ø­"ØŒ ÙˆÙ„Ø§ ØªØµØ­ Ø§Ù„ØªØ¶Ø­ÙŠØ© Ø¨Ø§Ù„ÙƒØ«ÙŠØ± ÙÙŠ Ø³Ø¨ÙŠÙ„ Ø§Ù„Ø­ØµÙˆÙ„ Ø¹Ù„Ù‰ Ø§Ù„Ù‚Ù„ÙŠÙ„.]]></document>
		<document><![CDATA[3
Ø¹Ù„Ù‰ Ø§Ù„ØµØ¹ÙŠØ¯ Ø§Ù„Ø¯Ø§Ø®Ù„ÙŠ Ù„Ø£ÙŠ Ø¯ÙˆÙ„Ø© ØªÙˆØ¬Ø¯ Ù„Ø¯Ù‰ Ø§Ù„Ø£ÙØ±Ø§Ø¯ Ù…ØµØ§Ù„Ø­ Ø®Ø§ØµØ© ÙˆØ¹Ø§Ù…Ø© Ù„ÙŠØ³Øª Ø¬Ù…ÙŠØ¹Ù‡Ø§ ÙÙŠ Ù…Ø±ØªØ¨Ø© ÙˆØ§Ø­Ø¯Ø©.
ÙÙ…Ù† Ù…ØµØ§Ù„Ø­ Ø¹Ù„ÙŠØ§ Ø§Ø³ØªØ±Ø§ØªÙŠØ¬ÙŠØ© Ù„Ù„Ø¯ÙˆÙ„Ø©ØŒ Ø¥Ù„Ù‰ Ù…ØµØ§Ù„Ø­ ÙˆÙ‚ØªÙŠØ© ÙŠÙ…ÙƒÙ† Ø§Ù„ØªÙ†Ø§Ø²Ù„ Ø¹Ù†Ù‡Ø§ Ø£Ùˆ ØªØ£Ø¬ÙŠÙ„Ù‡Ø§ Ø­Ø³Ø¨ Ø§Ù„Ø¸Ø±ÙˆÙ ÙˆØ§Ù„Ø£Ø­ÙˆØ§Ù„.
ÙˆØªØªØ¨Ø§ÙŠÙ† Ø§Ù„Ù…ØµØ§Ù„Ø­ØŒ ÙˆØªØªÙØ§ÙˆØªØŒ ÙˆÙŠØµØ¨Ø­ Ø§Ù„Ù…Ù…ÙƒÙ† ÙÙŠ ÙˆÙ‚Øª Ù…Ø­Ø§Ù„Ø§ ÙÙŠ ÙˆÙ‚Øª Ø¢Ø®Ø±ØŒ ÙˆØ§Ù„Ø¹ÙƒØ³ ÙƒØ°Ù„Ùƒ Ø­Ø³Ø¨ Ø§Ù„Ø£Ø­ÙˆØ§Ù„.]]></document>
		<document><![CDATA[2
Ø§Ù„ØªØ¹Ø§Ù…Ù„ Ù…Ø¹ Ù‡Ø°Ø§ Ø§Ù„ÙˆØ§Ù‚Ø¹ ØµØ¹Ø¨ Ù„Ù„ØºØ§ÙŠØ©Ø› Ù„Ø£Ù†Ù‡ ÙˆØ§Ù‚Ø¹ ØºÙŠØ± Ù…Ø³ØªÙ‚Ø± Ø¹Ù„Ù‰ Ø­Ø§Ù„ØŒ ÙˆÙ…Ø¹ Ø£Ù† Ø§Ù„Ù…ØµÙ„Ø­Ø© ØªÙ‚ÙˆØ¯ ÙÙŠ Ø£Ø­ÙŠØ§Ù† ÙƒØ«ÙŠØ±Ø© Ø¥Ù„Ù‰ ØªÙØ¶ÙŠÙ„ Ø§Ø¹ØªØ¨Ø§Ø±Ø§Øª Ø®Ø§ØµØ©ØŒ Ø¥Ù„Ø§ Ø£Ù† Ø§Ù„Ù…ØµÙ„Ø­Ø© Ø§Ù„Ø£ÙƒØ«Ø± Ø£Ù‡Ù…ÙŠØ© Ù‡ÙŠ Ø§Ù„Ù†Ø§ØªØ¬Ø© Ø¹Ù† ÙˆØ¹ÙŠ ÙˆØªØ®Ø·ÙŠØ· ÙˆØ¯Ø±Ø§Ø³Ø©ØŒ ÙˆØªÙƒÙˆÙ† Ù‡ÙŠ Ø§Ù„Ù…ØµÙ„Ø­Ø© Ø§Ù„Ø§Ø³ØªØ±Ø§ØªÙŠØ¬ÙŠØ© ÙˆØ§Ù„Ø¹Ù„ÙŠØ§ØŒ Ø§Ù„ØªÙŠ Ù„Ø§ ÙŠÙ…ÙƒÙ† Ù…Ù‚Ø§Ø±Ù†Ø© Ø§Ù„Ù…ØµØ§Ù„Ø­ Ø§Ù„Ø¢Ù†ÙŠÙ‘Ø© ÙˆØ§Ù„Ù…Ø¤Ù‚ØªØ© Ø¨Ù‡Ø§.]]></document>
		<document><![CDATA[1
Ù‚Ø¯ ØªÙƒÙˆÙ† Ù‡Ø°Ù‡ Ø§Ù„ÙØªØ±Ø© Ø§Ù„ØªÙŠ ØªÙ…Ø± Ø¨Ù‡Ø§ Ù…Ù†Ø·Ù‚ØªÙ†Ø§ ÙˆØ§Ø­Ø¯Ø© Ù…Ù† Ø£ØµØ¹Ø¨ Ø§Ù„ÙØªØ±Ø§ØªØŒ Ø§Ù„ØªÙŠ ØªØ­Ù…Ù„ ÙÙŠ Ø·ÙŠØ§ØªÙ‡Ø§ Ø§Ù„ÙƒØ«ÙŠØ± Ù…Ù† Ø§Ù„Ù…ØªØºÙŠØ±Ø§Øª ÙˆØ§Ù„Ù…Ø®Ø§Ø·Ø±ØŒ ÙˆØ§Ù„ØªÙƒØªÙ„Ø§Øª Ø§Ù„ØªÙŠ Ù„Ø§ ØªÙ‚ÙˆÙ… Ø¹Ù„Ù‰ Ù…Ù†Ù‡Ø¬ Ù…Ø³ØªÙ‚Ø±Ø› Ø¨Ø§Ø¹ØªØ¨Ø§Ø± Ø£Ù† Ø§Ù„Ø¥Ø±Ø§Ø¯Ø© Ø§Ù„ÙØ±Ø¯ÙŠØ© Ù‡ÙŠ Ø§Ù„ØªÙŠ ØªØ³ÙŠÙ‘Ø± ÙˆØ¬Ù‡Ø© Ø¨Ø¹Ø¶ Ø§Ù„Ø¯ÙˆÙ„ØŒ ÙˆÙ„ÙŠØ³ Ø§Ù„Ù…Ø¤Ø³Ø³Ø§Øª Ø§Ù„ØªÙŠ ØªØªÙ‘Ø¨Ø¹ Ø§Ù„Ø¯Ø±Ø§Ø³Ø§Øª Ø§Ù„Ø¹Ù„Ù…ÙŠØ© ÙˆØ§Ù„Ø§Ø³ØªØ±Ø§ØªÙŠØ¬ÙŠØ© ÙˆØ§Ù„Ù…Ù†Ù‡Ø¬ÙŠØ©.]]></document>
		<document><![CDATA[Ø±Ø³Ø§Ù„Ø© Ù„ÙˆØ¬Ù‡ Ø§Ù„ÙˆØ·Ù† ðŸ“©]]></document>
		<document><![CDATA[Ø¨Ø¹Ø¶ Ø§Ù„Ø­Ù‚Ø§Ø¦Ù‚ Ø§Ù„Ø®Ø§ØµØ© Ø¨Ù†Ø§ Ù†Ø¤Ù…Ù† Ø¨Ù‡Ø§ØŒ ÙˆØ¥Ù† ÙƒÙ†Ø§ Ù„Ø§ Ù†Ø­Ø¨Ù‡Ø§ØŒ ÙˆÙ„ÙƒÙ†Ù†Ø§ Ù†ØªØ£Ù„Ù… ÙƒØ«ÙŠØ±Ø§ Ø¥Ø°Ø§ Ù‚ÙŠÙ„Øª Ù„Ù†Ø§ Ù…Ù…Ù† Ù†Ø­Ø¨Ù‡Ù…!]]></document>
		<document><![CDATA[@ahmed_alhosni Ø³Ø±Ù†ÙŠ Ø§Ù„Ø®Ø¨Ø±.
ÙˆÙÙ‚ Ø§Ù„Ù„Ù‡ Ø§Ù„Ø£Ø³ØªØ§Ø° Ø§Ù„Ø±Ø§Ø¦Ø¹ Ù‡ÙŠØ«Ù….]]></document>
		<document><![CDATA[@_omarahinai_ @Umniyah1992 Ø§Ù„Ø¨Ø±]]></document>
		<document><![CDATA[@maryam_sam_93 @Umniyah1992 Ø®Ø§ØµØ© ÙÙŠ Ø±Ù…Ø¶Ø§Ù†.]]></document>
		<document><![CDATA[@Umniyah1992 Ù„Ø§ Ø£Ø¹Ø±Ù ðŸ˜]]></document>
		<document><![CDATA[@Umniyah1992 Ù„Ø§ Ø¥Ø¬Ø±Ø§Ø¡Ø§Øª.]]></document>
		<document><![CDATA[@ISYCWt9deUAHwkO Ù…Ø³Ø§Ø¡ Ø§Ù„Ù†ÙˆØ± Ø³ÙŠØ¯ÙŠ Ø§Ù„Ù…Ø­Ø¨.
Ù„ÙŠØª ÙÙ‡Ù…ÙŠ ÙŠØµÙ„ Ø¥Ù„Ù‰ Ø¹ÙØ´Ø± Ø¸Ù†Ùƒ Ø¨ÙŠ.
ðŸŒ¹]]></document>
		<document><![CDATA[@FahadAlismaili Ù„ÙŠØª Ø§Ù„ÙÙƒØ±Ø© ØªØ¤Ø®Ø° ÙÙŠ Ø§Ù„Ø­Ø³Ø¨Ø§Ù†.]]></document>
		<document><![CDATA[@AlhusanA Ù‡Ø°Ø§ Ù…ÙØ±ÙˆØº Ù…Ù†Ù‡.]]></document>
		<document><![CDATA[@amal_nasser10 ØªÙˆØ¬Ø¯ Ø£Ø­ÙƒØ§Ù… Ø¨Ø§Ù„Ø¥Ø¹Ø¯Ø§Ù….]]></document>
		<document><![CDATA[@alfarsia80 Ø§Ù„ÙÙƒØ±Ø© Ø¬Ù…ÙŠÙ„Ø©.]]></document>
		<document><![CDATA[Ù‡Ù„ ÙŠÙ…ÙƒÙ† Ø§Ø³ØªØ«Ù…Ø§Ø± Ø·Ø§Ù‚Ø§Øª Ø§Ù„Ø³Ø¬Ù†Ø§Ø¡ ÙÙŠ Ù…Ø´Ø§Ø±ÙŠØ¹ ÙƒÙ‡Ø°Ù‡ ðŸ‘‡ ØªØ¹ÙˆØ¯ Ø¹Ù„ÙŠÙ‡Ù… Ø¨Ø¯Ø®Ù„ Ø´Ù‡Ø±ÙŠØŒ ÙˆØªØ¬Ø¹Ù„ Ù…Ù† Ø­ÙŠØ§ØªÙ‡Ù… Ø¯Ø§Ø®Ù„ Ø§Ù„Ø³Ø¬ÙˆÙ† Ø°Ø§Øª Ù…Ø¹Ù†Ù‰ØŒ ÙˆØªØ¹ÙˆØ¯ Ø¹Ù„Ù‰ Ø§Ù„Ø¯ÙˆÙ„Ø© Ø¨Ø§Ù„ÙØ§Ø¦Ø¯Ø© ÙÙŠ Ù†ÙØ³ Ø§Ù„ÙˆÙ‚Øª. https://t.co/NgAzJeDWYs]]></document>
		<document><![CDATA[@za3_0 @Mawllay Ø§Ù„Ù„Ù‡ ÙŠØ³Ø¹Ø¯ÙƒÙ… ðŸ˜]]></document>
		<document><![CDATA[@albortomani Ù„Ø§ Ù…Ù‚Ø§Ø±Ù†Ø© Ø¨ÙŠÙ† Ø£Ù† ÙŠØ°Ù‡Ø¨ Ø¥Ù†Ø³Ø§Ù† Ø¨Ø¥Ø±Ø§Ø¯ØªÙ‡ Ø§Ù„Ø­Ø±Ø© Ø¥Ù„Ù‰ Ù…Ù…Ø§Ø±Ø³Ø© Ø±ÙŠØ§Ø¶Ø© Ø¹Ù†ÙŠÙØ©ØŒ ÙˆØ£Ù† ÙŠØ¤Ø®Ø° Ø­ÙŠÙˆØ§Ù† Ù„Ù…Ù…Ø§Ø±Ø³Ø© Ø¹Ù†ÙŠÙØ© Ø­ØªÙ‰ ÙŠØªÙƒØ³Ø¨ Ø£Ùˆ ÙŠØªÙ„Ø°Ø° Ø¨Ø°Ù„Ùƒ Ø¥Ù†Ø³Ø§Ù†.]]></document>
		<document><![CDATA[@albortomani Ù‡Ù„ Ù‡ÙŠ Ø±ÙŠØ§Ø¶Ø© Ù…ØµØ±Ø­Ø© ÙˆØªØ­ÙƒÙ…Ù‡Ø§ Ù‚ÙˆØ§Ø¹Ø¯ Ù…Ø«Ø¨ØªØ© Ù„Ø¯Ù‰ Ø¬Ù‡Ø§Øª Ø§Ù„Ø§Ø®ØªØµØ§ØµØŸ]]></document>
		<document><![CDATA[@mOYqVTAmrb3brbc Ø°Ù‡Ø¨ Ø§Ù„Ø°ÙŠÙ† ÙŠÙØ¹Ø§Ø´ ÙÙŠ Ø£ÙƒÙ†Ø§ÙÙ‡Ù…
ÙˆØ¨Ù‚Ù‰ Ø§Ù„Ø°ÙŠÙ† Ø­ÙŠØ§ØªÙ‡Ù… Ù„Ø§ ØªÙ†ÙØ¹.]]></document>
		<document><![CDATA[@WaelAlamri96 Ø§Ù„Ø£Ù…Ø± Ù„Ù„Ù…Ø­ÙƒÙ…Ø©.]]></document>
		<document><![CDATA[@WaelAlamri96 Ø¹Ù‚ÙˆØ¨Ø© Ø§Ù„Ø³Ø¬Ù† ØªØµÙ„ Ø¥Ù„Ù‰ Ø´Ù‡Ø±ØŒ ÙˆØªÙƒÙÙŠ Ù„Ù„Ø±Ø¯Ø¹.]]></document>
		<document><![CDATA[@tmashaikhi ÙˆØ§Ù„Ù‚Ø§Ù†ÙˆÙ† ÙŠØ¬Ø±Ù…Ù‡Ø§.]]></document>
		<document><![CDATA[@Maaaaaam18 Ù„Ù† ÙŠÙ‚ØµØ±ÙˆØ§ØŒ ÙˆØ§Ù„ØªØ´Ø±ÙŠØ¹ ÙŠØ³Ø¹ÙÙ‡Ù….]]></document>
		<document><![CDATA[@almuharrmi Ù„Ø±Ø¨Ù…Ø§ Ø£Ø±Ø§Ø¯Ù‡Ø§ Ø£Ø¹Ù…Ù‚ Ø¯Ù„Ø§Ù„Ø©Ù…Ù† Ø§Ù„Ù†Ø¸Ø±Ø© Ø§Ù„Ø¹Ø§Ø¯ÙŠØ© Ù„Ù…ÙÙ‡ÙˆÙ… Ø§Ù„Ø¹Ù‡Ø±ØŒ ÙˆÙ…Ø³ØªØ¨Ø¹Ø¯ Ø£Ù† ÙŠÙƒÙˆÙ† Ø¨ÙˆØªÙŠÙ† Ø§Ù„Ø´Ø®Øµ Ø§Ù„Ø°ÙŠ ÙŠÙ‚ÙˆÙ… Ø¨Ø¯ÙˆØ± Ø§Ù„Ù‚ÙˆØ§Ø¯Ø©.]]></document>
		<document><![CDATA[@alkalbani2007 Ù„Ùˆ ØºÙŠØ±Ùƒ Ø³Ø§Ø¦Ù„ÙŠ Ù„Ø£Ø¬Ø¨ØªÙ‡ ðŸ˜‰]]></document>
		<document><![CDATA[@hadoi92 @Ashayma0 Ø¥Ø°Ù† Ø¨Ø³ÙŠØ·Ø© ðŸ˜]]></document>
		<document><![CDATA[@Ashayma0 @hadoi92 Ø³Ù„Ø§Ù…Ø§Øª ðŸ˜³
Ù„ÙŠØ´ Ù†Ø²Ø­ÙˆØ§ ðŸ˜]]></document>
		<document><![CDATA[@hadoi92 Ù„ÙŠØ´ ÙˆÙŠÙ† Ø±Ø§Ø­ÙˆØ§ ðŸ˜³]]></document>
		<document><![CDATA[@Salfarsis ÙƒÙ„ Ù…Ø§ Ø°ÙƒØ±!]]></document>
		<document><![CDATA[@ialmukhtar Ø±Ø­Ù…Ù‡ Ø§Ù„Ù„Ù‡ ÙˆØ£Ø­Ø³Ù† Ø¹Ø²Ø§Ø¡ÙƒÙ….]]></document>
		<document><![CDATA[@alaamria_ Ù‡Ø°Ø§ Ø¬Ø§Ù†Ø¨ Ø¢Ø®Ø±.]]></document>
		<document><![CDATA[Ù…Ø§ØªÙˆØ§ Ù„ÙŠØ­ÙŠÙˆÙ’Ø§ØŒ ÙˆØ­ÙŠÙŠÙ†Ø§ Ù„Ù†Ù…ÙˆØªØŒ ÙÙ…Ù† Ø§Ù„ÙØ§Ù‚Ø¯ØŒ ÙˆÙ…Ù† Ø§Ù„Ù…ÙÙ‚ÙˆØ¯!]]></document>
		<document><![CDATA[@HasasW @8Alrahbi Ø§Ù„Ù„Ù‡]]></document>
		<document><![CDATA["Ù‚ÙØ¨ÙÙ„Ø§ØªÙÙ‡Ù… Ø¹Ø±Ø¨ÙŠØ©ÙŒ

Ù…ÙŽÙ† Ø°Ø§ Ø±Ø£Ù‰

ÙÙŠÙ…Ø§ Ø±Ø£Ù‰

Ù‚ÙØ¨ÙŽÙ„Ø§Ù‹ Ù„Ù‡Ø§ Ø£Ù†ÙŠØ§Ø¨Ù"!

Ù†Ø²Ø§Ø±]]></document>
		<document><![CDATA[@snavioman @HILAL_R2 Ø®Ù Ø¹Ù„ÙŠÙ‡Ù….]]></document>
		<document><![CDATA[@MAHmoodRashdi Ù„Ù„Ù‡ Ø§Ù„Ø¨Ù‚Ø§Ø¡]]></document>
		<document><![CDATA[@mu7tram ØªØºØ±ÙŠØ¯ØªÙŠ Ù…Ø­Ø¯Ø¯Ø©.]]></document>
		<document><![CDATA[@saifalshidhani Ø§Ù„Ù‚ÙŠÙ… Ù…Ø³Ø§Ø­Ø© Ø®ØµØ¨Ø© Ù„ÙŠØ²Ø±Ø¹ ÙƒÙ„ ÙÙŠÙ‡Ø§ Ù…Ø§ ÙŠÙ†Ø§Ø³Ø¨Ù‡ Ù…Ù† Ø´ØªÙ„Ø§Øª.]]></document>
		<document><![CDATA[@AliAbuali01010 Ù„ÙŠ Ù…Ø§ Ù‚Ù„ØªØŒ ÙˆÙ„Ùƒ Ù…Ø§ ÙÙ‡Ù…Øª.]]></document>
		<document><![CDATA[Ù‡Ø°Ø§ Ø§Ù„Ø±Ø¬Ù„ Ø¹Ù„Ø§Ù…Ø© ÙØ§Ø±Ù‚Ø© ÙÙŠ ØªØ§Ø±ÙŠØ® Ø§Ù„Ù…Ù…Ù„ÙƒØ©ØŒ ÙˆØ­Ø³Ø¨ Ù…ØªØ§Ø¨Ø¹ØªÙŠ ÙØ¥Ù†ÙŠ Ø£Ø±Ø§Ù‡ ÙŠÙ‚ÙˆØ¯Ù‡Ø§ Ù„ÙƒØªØ§Ø¨Ø© Ø­Ø§Ø¶Ø± Ù…Ø´Ø±Ù‚ ÙŠØªÙ„Ø§Ø¡Ù… ÙˆÙ…Ø§ ØªØªØ¬Ù‡ Ù„Ù‡ Ø§Ù„Ø­Ø¶Ø§Ø±Ø© Ø§Ù„Ù…Ø¯Ù†ÙŠØ© ÙÙŠ Ù‡Ø°Ø§ Ø§Ù„Ø¹ØµØ± Ù…Ù† Ø¨Ù†Ø§Ø¡ Ù„Ù„Ø¥Ù†Ø³Ø§Ù†ØŒ ÙˆØµÙ†Ø§Ø¹Ø© Ù„Ø­Ø§Ø¶Ø±  Ù…ØªÙ‚Ø¯Ù… ÙˆÙ…ØªØ·ÙˆØ±.
ÙˆÙ„Ù† ÙŠÙƒÙˆÙ† Ø§Ù„Ø·Ø±ÙŠÙ‚ Ù…ÙØ±ÙˆØ´Ø§ Ø¨Ø§Ù„ÙˆØ±ÙˆØ¯ØŒ ÙˆÙ„ÙƒÙ† Ø¹Ù„Ù‰ Ù‚Ø¯Ø± Ø£Ù‡Ù„ Ø§Ù„Ø¹Ø²Ù… ØªØ£ØªÙŠ Ø§Ù„Ø¹Ø²Ø§Ø¦Ù….

#Ù…Ø­Ù…Ø¯_Ø¨Ù†_Ø³Ù„Ù…Ø§Ù†_ØµØ§Ù†Ø¹_Ø§Ù„Ù…Ø³ØªÙ‚Ø¨Ù„]]></document>
		<document><![CDATA[@Alialhjri562 @AlhinaiMabrook Ù„Ù„Ù‡ Ø§Ù„Ø¨Ù‚Ø§Ø¡.]]></document>
		<document><![CDATA[@Amoula5alhasani ÙŠØ§ Ø±Ø¨]]></document>
	</documents>
	</author>